{"v":"5.6.5","fr":23.9759979248047,"ip":0,"op":119.999989613637,"w":768,"h":768,"nm":"scaning1","ddd":0,"assets":[],"layers":[{"ddd":0,"ind":2,"ty":4,"nm":"indicator","sr":1.44723036289301,"ks":{"o":{"a":0,"k":100,"ix":11},"r":{"a":0,"k":0,"ix":10},"p":{"a":0,"k":[384,150,0],"ix":2},"a":{"a":0,"k":[0,0,0],"ix":1},"s":{"a":0,"k":[100,100,100],"ix":6}},"ao":0,"shapes":[{"ty":"gr","it":[{"ind":0,"ty":"sh","ix":1,"ks":{"a":0,"k":{"i":[[0,0],[0,0]],"o":[[0,0],[0,0]],"v":[[0.75,-80],[0.75,24]],"c":false},"ix":2},"nm":"路径 1","mn":"ADBE Vector Shape - Group","hd":false},{"ty":"st","c":{"a":1,"k":[{"i":{"x":[0.833],"y":[0.833]},"o":{"x":[0.167],"y":[0.167]},"t":36,"s":[0.790025889874,0.807454049587,0.828094363213,1],"e":[0.121568627656,0.843137264252,0.68235296011,1]},{"i":{"x":[0.833],"y":[0.833]},"o":{"x":[0.167],"y":[0.167]},"t":38.894,"s":[0.121568627656,0.843137264252,0.68235296011,1],"e":[0.121568627656,0.843137264252,0.68235296011,1]},{"i":{"x":[0.833],"y":[0.833]},"o":{"x":[0.167],"y":[0.167]},"t":47.578,"s":[0.121568627656,0.843137264252,0.68235296011,1],"e":[0.790025889874,0.807454049587,0.828094363213,1]},{"t":50.4723272890675}],"ix":3},"o":{"a":0,"k":100,"ix":4},"w":{"a":0,"k":6,"ix":5},"lc":2,"lj":1,"ml":4,"bm":0,"nm":"描边 1","mn":"ADBE Vector Graphic - Stroke","hd":false},{"ty":"tm","s":{"a":1,"k":[{"i":{"x":[0.833],"y":[0.833]},"o":{"x":[0.167],"y":[0.167]},"t":36,"s":[60],"e":[42]},{"i":{"x":[0.833],"y":[0.833]},"o":{"x":[0.167],"y":[0.167]},"t":43.236,"s":[42],"e":[60]},{"t":50.4723272890675}],"ix":1},"e":{"a":0,"k":67,"ix":2},"o":{"a":0,"k":0,"ix":3},"m":1,"ix":3,"nm":"Trim Paths","mn":"ADBE Vector Filter - Trim","hd":false},{"ty":"tr","p":{"a":0,"k":[0,234],"ix":2},"a":{"a":0,"k":[0,234],"ix":1},"s":{"a":0,"k":[100,100],"ix":3},"r":{"a":0,"k":0.381,"ix":6},"o":{"a":0,"k":100,"ix":7},"sk":{"a":0,"k":0,"ix":4},"sa":{"a":0,"k":0,"ix":5},"nm":"Transform"}],"nm":"形状 1","np":3,"cix":2,"bm":0,"ix":1,"mn":"ADBE Vector Group","hd":false},{"ty":"gr","it":[{"ind":0,"ty":"sh","ix":1,"ks":{"a":0,"k":{"i":[[0,0],[0,0]],"o":[[0,0],[0,0]],"v":[[0.75,-80],[0.75,24]],"c":false},"ix":2},"nm":"路径 1","mn":"ADBE Vector Shape - Group","hd":false},{"ty":"st","c":{"a":1,"k":[{"i":{"x":[0.833],"y":[0.833]},"o":{"x":[0.167],"y":[0.167]},"t":37.187,"s":[0.790025889874,0.807454049587,0.828094363213,1],"e":[0.121568627656,0.843137264252,0.68235296011,1]},{"i":{"x":[0.833],"y":[0.833]},"o":{"x":[0.167],"y":[0.167]},"t":40.342,"s":[0.121568627656,0.843137264252,0.68235296011,1],"e":[0.121568627656,0.843137264252,0.68235296011,1]},{"i":{"x":[0.833],"y":[0.833]},"o":{"x":[0.167],"y":[0.167]},"t":48.764,"s":[0.121568627656,0.843137264252,0.68235296011,1],"e":[0.790025889874,0.807454049587,0.828094363213,1]},{"t":51.6593543890335}],"ix":3},"o":{"a":0,"k":100,"ix":4},"w":{"a":0,"k":6,"ix":5},"lc":2,"lj":1,"ml":4,"bm":0,"nm":"描边 1","mn":"ADBE Vector Graphic - Stroke","hd":false},{"ty":"tm","s":{"a":1,"k":[{"i":{"x":[0.833],"y":[0.833]},"o":{"x":[0.167],"y":[0.167]},"t":37.187,"s":[60],"e":[42]},{"i":{"x":[0.833],"y":[0.833]},"o":{"x":[0.167],"y":[0.167]},"t":44.423,"s":[42],"e":[60]},{"t":51.6593543890335}],"ix":1},"e":{"a":0,"k":67,"ix":2},"o":{"a":0,"k":0,"ix":3},"m":1,"ix":3,"nm":"Trim Paths","mn":"ADBE Vector Filter - Trim","hd":false},{"ty":"tr","p":{"a":0,"k":[0,234],"ix":2},"a":{"a":0,"k":[0,234],"ix":1},"s":{"a":0,"k":[100,100],"ix":3},"r":{"a":0,"k":6,"ix":6},"o":{"a":0,"k":100,"ix":7},"sk":{"a":0,"k":0,"ix":4},"sa":{"a":0,"k":0,"ix":5},"nm":"Transform"}],"nm":"形状 2","np":3,"cix":2,"bm":0,"ix":2,"mn":"ADBE Vector Group","hd":false},{"ty":"gr","it":[{"ind":0,"ty":"sh","ix":1,"ks":{"a":0,"k":{"i":[[0,0],[0,0]],"o":[[0,0],[0,0]],"v":[[0.75,-80],[0.75,24]],"c":false},"ix":2},"nm":"路径 1","mn":"ADBE Vector Shape - Group","hd":false},{"ty":"st","c":{"a":1,"k":[{"i":{"x":[0.833],"y":[0.833]},"o":{"x":[0.167],"y":[0.167]},"t":38.359,"s":[0.790025889874,0.807454049587,0.828094363213,1],"e":[0.121568627656,0.843137264252,0.68235296011,1]},{"i":{"x":[0.833],"y":[0.833]},"o":{"x":[0.167],"y":[0.167]},"t":41.253,"s":[0.121568627656,0.843137264252,0.68235296011,1],"e":[0.121568627656,0.843137264252,0.68235296011,1]},{"i":{"x":[0.833],"y":[0.833]},"o":{"x":[0.167],"y":[0.167]},"t":49.937,"s":[0.121568627656,0.843137264252,0.68235296011,1],"e":[0.790025889874,0.807454049587,0.828094363213,1]},{"t":52.8313811465398}],"ix":3},"o":{"a":0,"k":100,"ix":4},"w":{"a":0,"k":6,"ix":5},"lc":2,"lj":1,"ml":4,"bm":0,"nm":"描边 1","mn":"ADBE Vector Graphic - Stroke","hd":false},{"ty":"tm","s":{"a":1,"k":[{"i":{"x":[0.833],"y":[0.833]},"o":{"x":[0.167],"y":[0.167]},"t":38.359,"s":[60],"e":[42]},{"i":{"x":[0.833],"y":[0.833]},"o":{"x":[0.167],"y":[0.167]},"t":45.595,"s":[42],"e":[60]},{"t":52.8313811465398}],"ix":1},"e":{"a":0,"k":67,"ix":2},"o":{"a":0,"k":0,"ix":3},"m":1,"ix":3,"nm":"Trim Paths","mn":"ADBE Vector Filter - Trim","hd":false},{"ty":"tr","p":{"a":0,"k":[0,234],"ix":2},"a":{"a":0,"k":[0,234],"ix":1},"s":{"a":0,"k":[100,100],"ix":3},"r":{"a":0,"k":12,"ix":6},"o":{"a":0,"k":100,"ix":7},"sk":{"a":0,"k":0,"ix":4},"sa":{"a":0,"k":0,"ix":5},"nm":"Transform"}],"nm":"形状 3","np":3,"cix":2,"bm":0,"ix":3,"mn":"ADBE Vector Group","hd":false},{"ty":"gr","it":[{"ind":0,"ty":"sh","ix":1,"ks":{"a":0,"k":{"i":[[0,0],[0,0]],"o":[[0,0],[0,0]],"v":[[0.75,-80],[0.75,24]],"c":false},"ix":2},"nm":"路径 1","mn":"ADBE Vector Shape - Group","hd":false},{"ty":"st","c":{"a":1,"k":[{"i":{"x":[0.833],"y":[0.833]},"o":{"x":[0.167],"y":[0.167]},"t":39.546,"s":[0.790025889874,0.807454049587,0.828094363213,1],"e":[0.121568627656,0.843137264252,0.68235296011,1]},{"i":{"x":[0.833],"y":[0.833]},"o":{"x":[0.167],"y":[0.167]},"t":42.44,"s":[0.121568627656,0.843137264252,0.68235296011,1],"e":[0.121568627656,0.843137264252,0.68235296011,1]},{"i":{"x":[0.833],"y":[0.833]},"o":{"x":[0.167],"y":[0.167]},"t":51.123,"s":[0.121568627656,0.843137264252,0.68235296011,1],"e":[0.790025889874,0.807454049587,0.828094363213,1]},{"t":54.0184082465058}],"ix":3},"o":{"a":0,"k":100,"ix":4},"w":{"a":0,"k":6,"ix":5},"lc":2,"lj":1,"ml":4,"bm":0,"nm":"描边 1","mn":"ADBE Vector Graphic - Stroke","hd":false},{"ty":"tm","s":{"a":1,"k":[{"i":{"x":[0.833],"y":[0.833]},"o":{"x":[0.167],"y":[0.167]},"t":39.546,"s":[60],"e":[42]},{"i":{"x":[0.833],"y":[0.833]},"o":{"x":[0.167],"y":[0.167]},"t":46.782,"s":[42],"e":[60]},{"t":54.0184082465058}],"ix":1},"e":{"a":0,"k":67,"ix":2},"o":{"a":0,"k":0,"ix":3},"m":1,"ix":3,"nm":"Trim Paths","mn":"ADBE Vector Filter - Trim","hd":false},{"ty":"tr","p":{"a":0,"k":[0,234],"ix":2},"a":{"a":0,"k":[0,234],"ix":1},"s":{"a":0,"k":[100,100],"ix":3},"r":{"a":0,"k":18,"ix":6},"o":{"a":0,"k":100,"ix":7},"sk":{"a":0,"k":0,"ix":4},"sa":{"a":0,"k":0,"ix":5},"nm":"Transform"}],"nm":"形状 4","np":3,"cix":2,"bm":0,"ix":4,"mn":"ADBE Vector Group","hd":false},{"ty":"gr","it":[{"ind":0,"ty":"sh","ix":1,"ks":{"a":0,"k":{"i":[[0,0],[0,0]],"o":[[0,0],[0,0]],"v":[[0.75,-80],[0.75,24]],"c":false},"ix":2},"nm":"路径 1","mn":"ADBE Vector Shape - Group","hd":false},{"ty":"st","c":{"a":1,"k":[{"i":{"x":[0.833],"y":[0.833]},"o":{"x":[0.167],"y":[0.167]},"t":40.718,"s":[0.790025889874,0.807454049587,0.828094363213,1],"e":[0.121568627656,0.843137264252,0.68235296011,1]},{"i":{"x":[0.833],"y":[0.833]},"o":{"x":[0.167],"y":[0.167]},"t":43.612,"s":[0.121568627656,0.843137264252,0.68235296011,1],"e":[0.121568627656,0.843137264252,0.68235296011,1]},{"i":{"x":[0.833],"y":[0.833]},"o":{"x":[0.167],"y":[0.167]},"t":52.295,"s":[0.121568627656,0.843137264252,0.68235296011,1],"e":[0.790025889874,0.807454049587,0.828094363213,1]},{"t":55.1904350040122}],"ix":3},"o":{"a":0,"k":100,"ix":4},"w":{"a":0,"k":6,"ix":5},"lc":2,"lj":1,"ml":4,"bm":0,"nm":"描边 1","mn":"ADBE Vector Graphic - Stroke","hd":false},{"ty":"tm","s":{"a":1,"k":[{"i":{"x":[0.833],"y":[0.833]},"o":{"x":[0.167],"y":[0.167]},"t":40.718,"s":[60],"e":[42]},{"i":{"x":[0.833],"y":[0.833]},"o":{"x":[0.167],"y":[0.167]},"t":47.954,"s":[42],"e":[60]},{"t":55.1904350040122}],"ix":1},"e":{"a":0,"k":67,"ix":2},"o":{"a":0,"k":0,"ix":3},"m":1,"ix":3,"nm":"Trim Paths","mn":"ADBE Vector Filter - Trim","hd":false},{"ty":"tr","p":{"a":0,"k":[0,234],"ix":2},"a":{"a":0,"k":[0,234],"ix":1},"s":{"a":0,"k":[100,100],"ix":3},"r":{"a":0,"k":24,"ix":6},"o":{"a":0,"k":100,"ix":7},"sk":{"a":0,"k":0,"ix":4},"sa":{"a":0,"k":0,"ix":5},"nm":"Transform"}],"nm":"形状 5","np":3,"cix":2,"bm":0,"ix":5,"mn":"ADBE Vector Group","hd":false},{"ty":"gr","it":[{"ind":0,"ty":"sh","ix":1,"ks":{"a":0,"k":{"i":[[0,0],[0,0]],"o":[[0,0],[0,0]],"v":[[0.75,-80],[0.75,24]],"c":false},"ix":2},"nm":"路径 1","mn":"ADBE Vector Shape - Group","hd":false},{"ty":"st","c":{"a":1,"k":[{"i":{"x":[0.833],"y":[0.833]},"o":{"x":[0.167],"y":[0.167]},"t":41.89,"s":[0.790025889874,0.807454049587,0.828094363213,1],"e":[0.121568627656,0.843137264252,0.68235296011,1]},{"i":{"x":[0.833],"y":[0.833]},"o":{"x":[0.167],"y":[0.167]},"t":44.784,"s":[0.121568627656,0.843137264252,0.68235296011,1],"e":[0.121568627656,0.843137264252,0.68235296011,1]},{"i":{"x":[0.833],"y":[0.833]},"o":{"x":[0.167],"y":[0.167]},"t":53.468,"s":[0.121568627656,0.843137264252,0.68235296011,1],"e":[0.790025889874,0.807454049587,0.828094363213,1]},{"t":56.3624617615186}],"ix":3},"o":{"a":0,"k":100,"ix":4},"w":{"a":0,"k":6,"ix":5},"lc":2,"lj":1,"ml":4,"bm":0,"nm":"描边 1","mn":"ADBE Vector Graphic - Stroke","hd":false},{"ty":"tm","s":{"a":1,"k":[{"i":{"x":[0.833],"y":[0.833]},"o":{"x":[0.167],"y":[0.167]},"t":41.89,"s":[60],"e":[42]},{"i":{"x":[0.833],"y":[0.833]},"o":{"x":[0.167],"y":[0.167]},"t":49.126,"s":[42],"e":[60]},{"t":56.3624617615186}],"ix":1},"e":{"a":0,"k":67,"ix":2},"o":{"a":0,"k":0,"ix":3},"m":1,"ix":3,"nm":"Trim Paths","mn":"ADBE Vector Filter - Trim","hd":false},{"ty":"tr","p":{"a":0,"k":[0,234],"ix":2},"a":{"a":0,"k":[0,234],"ix":1},"s":{"a":0,"k":[100,100],"ix":3},"r":{"a":0,"k":30,"ix":6},"o":{"a":0,"k":100,"ix":7},"sk":{"a":0,"k":0,"ix":4},"sa":{"a":0,"k":0,"ix":5},"nm":"Transform"}],"nm":"形状 6","np":3,"cix":2,"bm":0,"ix":6,"mn":"ADBE Vector Group","hd":false},{"ty":"gr","it":[{"ind":0,"ty":"sh","ix":1,"ks":{"a":0,"k":{"i":[[0,0],[0,0]],"o":[[0,0],[0,0]],"v":[[0.75,-80],[0.75,24]],"c":false},"ix":2},"nm":"路径 1","mn":"ADBE Vector Shape - Group","hd":false},{"ty":"st","c":{"a":1,"k":[{"i":{"x":[0.833],"y":[0.833]},"o":{"x":[0.167],"y":[0.167]},"t":43.077,"s":[0.790025889874,0.807454049587,0.828094363213,1],"e":[0.121568627656,0.843137264252,0.68235296011,1]},{"i":{"x":[0.833],"y":[0.833]},"o":{"x":[0.167],"y":[0.167]},"t":45.971,"s":[0.121568627656,0.843137264252,0.68235296011,1],"e":[0.121568627656,0.843137264252,0.68235296011,1]},{"i":{"x":[0.833],"y":[0.833]},"o":{"x":[0.167],"y":[0.167]},"t":54.654,"s":[0.121568627656,0.843137264252,0.68235296011,1],"e":[0.790025889874,0.807454049587,0.828094363213,1]},{"t":57.5494888614845}],"ix":3},"o":{"a":0,"k":100,"ix":4},"w":{"a":0,"k":6,"ix":5},"lc":2,"lj":1,"ml":4,"bm":0,"nm":"描边 1","mn":"ADBE Vector Graphic - Stroke","hd":false},{"ty":"tm","s":{"a":1,"k":[{"i":{"x":[0.833],"y":[0.833]},"o":{"x":[0.167],"y":[0.167]},"t":43.077,"s":[60],"e":[42]},{"i":{"x":[0.833],"y":[0.833]},"o":{"x":[0.167],"y":[0.167]},"t":50.313,"s":[42],"e":[60]},{"t":57.5494888614845}],"ix":1},"e":{"a":0,"k":67,"ix":2},"o":{"a":0,"k":0,"ix":3},"m":1,"ix":3,"nm":"Trim Paths","mn":"ADBE Vector Filter - Trim","hd":false},{"ty":"tr","p":{"a":0,"k":[0,234],"ix":2},"a":{"a":0,"k":[0,234],"ix":1},"s":{"a":0,"k":[100,100],"ix":3},"r":{"a":0,"k":36,"ix":6},"o":{"a":0,"k":100,"ix":7},"sk":{"a":0,"k":0,"ix":4},"sa":{"a":0,"k":0,"ix":5},"nm":"Transform"}],"nm":"形状 7","np":3,"cix":2,"bm":0,"ix":7,"mn":"ADBE Vector Group","hd":false},{"ty":"gr","it":[{"ind":0,"ty":"sh","ix":1,"ks":{"a":0,"k":{"i":[[0,0],[0,0]],"o":[[0,0],[0,0]],"v":[[0.75,-80],[0.75,24]],"c":false},"ix":2},"nm":"路径 1","mn":"ADBE Vector Shape - Group","hd":false},{"ty":"st","c":{"a":1,"k":[{"i":{"x":[0.833],"y":[0.833]},"o":{"x":[0.167],"y":[0.167]},"t":44.249,"s":[0.790025889874,0.807454049587,0.828094363213,1],"e":[0.121568627656,0.843137264252,0.68235296011,1]},{"i":{"x":[0.833],"y":[0.833]},"o":{"x":[0.167],"y":[0.167]},"t":47.143,"s":[0.121568627656,0.843137264252,0.68235296011,1],"e":[0.121568627656,0.843137264252,0.68235296011,1]},{"i":{"x":[0.833],"y":[0.833]},"o":{"x":[0.167],"y":[0.167]},"t":55.827,"s":[0.121568627656,0.843137264252,0.68235296011,1],"e":[0.790025889874,0.807454049587,0.828094363213,1]},{"t":58.7215156189909}],"ix":3},"o":{"a":0,"k":100,"ix":4},"w":{"a":0,"k":6,"ix":5},"lc":2,"lj":1,"ml":4,"bm":0,"nm":"描边 1","mn":"ADBE Vector Graphic - Stroke","hd":false},{"ty":"tm","s":{"a":1,"k":[{"i":{"x":[0.833],"y":[0.833]},"o":{"x":[0.167],"y":[0.167]},"t":44.249,"s":[60],"e":[42]},{"i":{"x":[0.833],"y":[0.833]},"o":{"x":[0.167],"y":[0.167]},"t":51.485,"s":[42],"e":[60]},{"t":58.7215156189909}],"ix":1},"e":{"a":0,"k":67,"ix":2},"o":{"a":0,"k":0,"ix":3},"m":1,"ix":3,"nm":"Trim Paths","mn":"ADBE Vector Filter - Trim","hd":false},{"ty":"tr","p":{"a":0,"k":[0,234],"ix":2},"a":{"a":0,"k":[0,234],"ix":1},"s":{"a":0,"k":[100,100],"ix":3},"r":{"a":0,"k":42,"ix":6},"o":{"a":0,"k":100,"ix":7},"sk":{"a":0,"k":0,"ix":4},"sa":{"a":0,"k":0,"ix":5},"nm":"Transform"}],"nm":"形状 8","np":3,"cix":2,"bm":0,"ix":8,"mn":"ADBE Vector Group","hd":false},{"ty":"gr","it":[{"ind":0,"ty":"sh","ix":1,"ks":{"a":0,"k":{"i":[[0,0],[0,0]],"o":[[0,0],[0,0]],"v":[[0.75,-80],[0.75,24]],"c":false},"ix":2},"nm":"路径 1","mn":"ADBE Vector Shape - Group","hd":false},{"ty":"st","c":{"a":1,"k":[{"i":{"x":[0.833],"y":[0.833]},"o":{"x":[0.167],"y":[0.167]},"t":45.421,"s":[0.790025889874,0.807454049587,0.828094363213,1],"e":[0.121568627656,0.843137264252,0.68235296011,1]},{"i":{"x":[0.833],"y":[0.833]},"o":{"x":[0.167],"y":[0.167]},"t":48.316,"s":[0.121568627656,0.843137264252,0.68235296011,1],"e":[0.121568627656,0.843137264252,0.68235296011,1]},{"i":{"x":[0.833],"y":[0.833]},"o":{"x":[0.167],"y":[0.167]},"t":56.999,"s":[0.121568627656,0.843137264252,0.68235296011,1],"e":[0.790025889874,0.807454049587,0.828094363213,1]},{"t":59.8935423764972}],"ix":3},"o":{"a":0,"k":100,"ix":4},"w":{"a":0,"k":6,"ix":5},"lc":2,"lj":1,"ml":4,"bm":0,"nm":"描边 1","mn":"ADBE Vector Graphic - Stroke","hd":false},{"ty":"tm","s":{"a":1,"k":[{"i":{"x":[0.833],"y":[0.833]},"o":{"x":[0.167],"y":[0.167]},"t":45.421,"s":[60],"e":[42]},{"i":{"x":[0.833],"y":[0.833]},"o":{"x":[0.167],"y":[0.167]},"t":52.657,"s":[42],"e":[60]},{"t":59.8935423764972}],"ix":1},"e":{"a":0,"k":67,"ix":2},"o":{"a":0,"k":0,"ix":3},"m":1,"ix":3,"nm":"Trim Paths","mn":"ADBE Vector Filter - Trim","hd":false},{"ty":"tr","p":{"a":0,"k":[0,234],"ix":2},"a":{"a":0,"k":[0,234],"ix":1},"s":{"a":0,"k":[100,100],"ix":3},"r":{"a":0,"k":48,"ix":6},"o":{"a":0,"k":100,"ix":7},"sk":{"a":0,"k":0,"ix":4},"sa":{"a":0,"k":0,"ix":5},"nm":"Transform"}],"nm":"形状 9","np":3,"cix":2,"bm":0,"ix":9,"mn":"ADBE Vector Group","hd":false},{"ty":"gr","it":[{"ind":0,"ty":"sh","ix":1,"ks":{"a":0,"k":{"i":[[0,0],[0,0]],"o":[[0,0],[0,0]],"v":[[0.75,-80],[0.75,24]],"c":false},"ix":2},"nm":"路径 1","mn":"ADBE Vector Shape - Group","hd":false},{"ty":"st","c":{"a":1,"k":[{"i":{"x":[0.833],"y":[0.833]},"o":{"x":[0.167],"y":[0.167]},"t":46.608,"s":[0.790025889874,0.807454049587,0.828094363213,1],"e":[0.121568627656,0.843137264252,0.68235296011,1]},{"i":{"x":[0.833],"y":[0.833]},"o":{"x":[0.167],"y":[0.167]},"t":49.502,"s":[0.121568627656,0.843137264252,0.68235296011,1],"e":[0.121568627656,0.843137264252,0.68235296011,1]},{"i":{"x":[0.833],"y":[0.833]},"o":{"x":[0.167],"y":[0.167]},"t":58.187,"s":[0.121568627656,0.843137264252,0.68235296011,1],"e":[0.790025889874,0.807454049587,0.828094363213,1]},{"t":61.0805694764632}],"ix":3},"o":{"a":0,"k":100,"ix":4},"w":{"a":0,"k":6,"ix":5},"lc":2,"lj":1,"ml":4,"bm":0,"nm":"描边 1","mn":"ADBE Vector Graphic - Stroke","hd":false},{"ty":"tm","s":{"a":1,"k":[{"i":{"x":[0.833],"y":[0.833]},"o":{"x":[0.167],"y":[0.167]},"t":46.608,"s":[60],"e":[42]},{"i":{"x":[0.833],"y":[0.833]},"o":{"x":[0.167],"y":[0.167]},"t":53.844,"s":[42],"e":[60]},{"t":61.0805694764632}],"ix":1},"e":{"a":0,"k":67,"ix":2},"o":{"a":0,"k":0,"ix":3},"m":1,"ix":3,"nm":"Trim Paths","mn":"ADBE Vector Filter - Trim","hd":false},{"ty":"tr","p":{"a":0,"k":[0,234],"ix":2},"a":{"a":0,"k":[0,234],"ix":1},"s":{"a":0,"k":[100,100],"ix":3},"r":{"a":0,"k":54,"ix":6},"o":{"a":0,"k":100,"ix":7},"sk":{"a":0,"k":0,"ix":4},"sa":{"a":0,"k":0,"ix":5},"nm":"Transform"}],"nm":"形状 10","np":3,"cix":2,"bm":0,"ix":10,"mn":"ADBE Vector Group","hd":false},{"ty":"gr","it":[{"ind":0,"ty":"sh","ix":1,"ks":{"a":0,"k":{"i":[[0,0],[0,0]],"o":[[0,0],[0,0]],"v":[[0.75,-80],[0.75,24]],"c":false},"ix":2},"nm":"路径 1","mn":"ADBE Vector Shape - Group","hd":false},{"ty":"st","c":{"a":1,"k":[{"i":{"x":[0.833],"y":[0.833]},"o":{"x":[0.167],"y":[0.167]},"t":47.78,"s":[0.790025889874,0.807454049587,0.828094363213,1],"e":[0.121568627656,0.843137264252,0.68235296011,1]},{"i":{"x":[0.833],"y":[0.833]},"o":{"x":[0.167],"y":[0.167]},"t":50.472,"s":[0.121568627656,0.843137264252,0.68235296011,1],"e":[0.121568627656,0.843137264252,0.68235296011,1]},{"i":{"x":[0.833],"y":[0.833]},"o":{"x":[0.167],"y":[0.167]},"t":59.359,"s":[0.121568627656,0.843137264252,0.68235296011,1],"e":[0.790025889874,0.807454049587,0.828094363213,1]},{"t":62.2525962339696}],"ix":3},"o":{"a":0,"k":100,"ix":4},"w":{"a":0,"k":6,"ix":5},"lc":2,"lj":1,"ml":4,"bm":0,"nm":"描边 1","mn":"ADBE Vector Graphic - Stroke","hd":false},{"ty":"tm","s":{"a":1,"k":[{"i":{"x":[0.833],"y":[0.833]},"o":{"x":[0.167],"y":[0.167]},"t":47.78,"s":[60],"e":[42]},{"i":{"x":[0.833],"y":[0.833]},"o":{"x":[0.167],"y":[0.167]},"t":55.016,"s":[42],"e":[60]},{"t":62.2525962339696}],"ix":1},"e":{"a":0,"k":67,"ix":2},"o":{"a":0,"k":0,"ix":3},"m":1,"ix":3,"nm":"Trim Paths","mn":"ADBE Vector Filter - Trim","hd":false},{"ty":"tr","p":{"a":0,"k":[0,234],"ix":2},"a":{"a":0,"k":[0,234],"ix":1},"s":{"a":0,"k":[100,100],"ix":3},"r":{"a":0,"k":60,"ix":6},"o":{"a":0,"k":100,"ix":7},"sk":{"a":0,"k":0,"ix":4},"sa":{"a":0,"k":0,"ix":5},"nm":"Transform"}],"nm":"形状 11","np":3,"cix":2,"bm":0,"ix":11,"mn":"ADBE Vector Group","hd":false},{"ty":"gr","it":[{"ind":0,"ty":"sh","ix":1,"ks":{"a":0,"k":{"i":[[0,0],[0,0]],"o":[[0,0],[0,0]],"v":[[0.75,-80],[0.75,24]],"c":false},"ix":2},"nm":"路径 1","mn":"ADBE Vector Shape - Group","hd":false},{"ty":"st","c":{"a":1,"k":[{"i":{"x":[0.833],"y":[0.833]},"o":{"x":[0.167],"y":[0.167]},"t":48.952,"s":[0.790025889874,0.807454049587,0.828094363213,1],"e":[0.121568627656,0.843137264252,0.68235296011,1]},{"i":{"x":[0.833],"y":[0.833]},"o":{"x":[0.167],"y":[0.167]},"t":51.847,"s":[0.121568627656,0.843137264252,0.68235296011,1],"e":[0.121568627656,0.843137264252,0.68235296011,1]},{"i":{"x":[0.833],"y":[0.833]},"o":{"x":[0.167],"y":[0.167]},"t":60.531,"s":[0.121568627656,0.843137264252,0.68235296011,1],"e":[0.790025889874,0.807454049587,0.828094363213,1]},{"t":63.4246229914759}],"ix":3},"o":{"a":0,"k":100,"ix":4},"w":{"a":0,"k":6,"ix":5},"lc":2,"lj":1,"ml":4,"bm":0,"nm":"描边 1","mn":"ADBE Vector Graphic - Stroke","hd":false},{"ty":"tm","s":{"a":1,"k":[{"i":{"x":[0.833],"y":[0.833]},"o":{"x":[0.167],"y":[0.167]},"t":48.952,"s":[60],"e":[42]},{"i":{"x":[0.833],"y":[0.833]},"o":{"x":[0.167],"y":[0.167]},"t":56.188,"s":[42],"e":[60]},{"t":63.4246229914759}],"ix":1},"e":{"a":0,"k":67,"ix":2},"o":{"a":0,"k":0,"ix":3},"m":1,"ix":3,"nm":"Trim Paths","mn":"ADBE Vector Filter - Trim","hd":false},{"ty":"tr","p":{"a":0,"k":[0,234],"ix":2},"a":{"a":0,"k":[0,234],"ix":1},"s":{"a":0,"k":[100,100],"ix":3},"r":{"a":0,"k":66,"ix":6},"o":{"a":0,"k":100,"ix":7},"sk":{"a":0,"k":0,"ix":4},"sa":{"a":0,"k":0,"ix":5},"nm":"Transform"}],"nm":"形状 12","np":3,"cix":2,"bm":0,"ix":12,"mn":"ADBE Vector Group","hd":false},{"ty":"gr","it":[{"ind":0,"ty":"sh","ix":1,"ks":{"a":0,"k":{"i":[[0,0],[0,0]],"o":[[0,0],[0,0]],"v":[[0.75,-80],[0.75,24]],"c":false},"ix":2},"nm":"路径 1","mn":"ADBE Vector Shape - Group","hd":false},{"ty":"st","c":{"a":1,"k":[{"i":{"x":[0.833],"y":[0.833]},"o":{"x":[0.167],"y":[0.167]},"t":50.139,"s":[0.790025889874,0.807454049587,0.828094363213,1],"e":[0.121568627656,0.843137264252,0.68235296011,1]},{"i":{"x":[0.833],"y":[0.833]},"o":{"x":[0.167],"y":[0.167]},"t":53.034,"s":[0.121568627656,0.843137264252,0.68235296011,1],"e":[0.121568627656,0.843137264252,0.68235296011,1]},{"i":{"x":[0.833],"y":[0.833]},"o":{"x":[0.167],"y":[0.167]},"t":61.718,"s":[0.121568627656,0.843137264252,0.68235296011,1],"e":[0.790025889874,0.807454049587,0.828094363213,1]},{"t":64.6116500914419}],"ix":3},"o":{"a":0,"k":100,"ix":4},"w":{"a":0,"k":6,"ix":5},"lc":2,"lj":1,"ml":4,"bm":0,"nm":"描边 1","mn":"ADBE Vector Graphic - Stroke","hd":false},{"ty":"tm","s":{"a":1,"k":[{"i":{"x":[0.833],"y":[0.833]},"o":{"x":[0.167],"y":[0.167]},"t":50.139,"s":[60],"e":[42]},{"i":{"x":[0.833],"y":[0.833]},"o":{"x":[0.167],"y":[0.167]},"t":57.375,"s":[42],"e":[60]},{"t":64.6116500914419}],"ix":1},"e":{"a":0,"k":67,"ix":2},"o":{"a":0,"k":0,"ix":3},"m":1,"ix":3,"nm":"Trim Paths","mn":"ADBE Vector Filter - Trim","hd":false},{"ty":"tr","p":{"a":0,"k":[0,234],"ix":2},"a":{"a":0,"k":[0,234],"ix":1},"s":{"a":0,"k":[100,100],"ix":3},"r":{"a":0,"k":72,"ix":6},"o":{"a":0,"k":100,"ix":7},"sk":{"a":0,"k":0,"ix":4},"sa":{"a":0,"k":0,"ix":5},"nm":"Transform"}],"nm":"形状 13","np":3,"cix":2,"bm":0,"ix":13,"mn":"ADBE Vector Group","hd":false},{"ty":"gr","it":[{"ind":0,"ty":"sh","ix":1,"ks":{"a":0,"k":{"i":[[0,0],[0,0]],"o":[[0,0],[0,0]],"v":[[0.75,-80],[0.75,24]],"c":false},"ix":2},"nm":"路径 1","mn":"ADBE Vector Shape - Group","hd":false},{"ty":"st","c":{"a":1,"k":[{"i":{"x":[0.833],"y":[0.833]},"o":{"x":[0.167],"y":[0.167]},"t":51.311,"s":[0.790025889874,0.807454049587,0.828094363213,1],"e":[0.121568627656,0.843137264252,0.68235296011,1]},{"i":{"x":[0.833],"y":[0.833]},"o":{"x":[0.167],"y":[0.167]},"t":54.206,"s":[0.121568627656,0.843137264252,0.68235296011,1],"e":[0,0.709803938866,0.388235300779,1]},{"i":{"x":[0.833],"y":[0.833]},"o":{"x":[0.167],"y":[0.167]},"t":62.89,"s":[0,0.709803938866,0.388235300779,1],"e":[0.790025889874,0.807454049587,0.828094363213,1]},{"t":65.7836768489483}],"ix":3},"o":{"a":0,"k":100,"ix":4},"w":{"a":0,"k":6,"ix":5},"lc":2,"lj":1,"ml":4,"bm":0,"nm":"描边 1","mn":"ADBE Vector Graphic - Stroke","hd":false},{"ty":"tm","s":{"a":1,"k":[{"i":{"x":[0.833],"y":[0.833]},"o":{"x":[0.167],"y":[0.167]},"t":51.311,"s":[60],"e":[42]},{"i":{"x":[0.833],"y":[0.833]},"o":{"x":[0.167],"y":[0.167]},"t":58.548,"s":[42],"e":[60]},{"t":65.7836768489483}],"ix":1},"e":{"a":0,"k":67,"ix":2},"o":{"a":0,"k":0,"ix":3},"m":1,"ix":3,"nm":"Trim Paths","mn":"ADBE Vector Filter - Trim","hd":false},{"ty":"tr","p":{"a":0,"k":[0,234],"ix":2},"a":{"a":0,"k":[0,234],"ix":1},"s":{"a":0,"k":[100,100],"ix":3},"r":{"a":0,"k":78,"ix":6},"o":{"a":0,"k":100,"ix":7},"sk":{"a":0,"k":0,"ix":4},"sa":{"a":0,"k":0,"ix":5},"nm":"Transform"}],"nm":"形状 14","np":3,"cix":2,"bm":0,"ix":14,"mn":"ADBE Vector Group","hd":false},{"ty":"gr","it":[{"ind":0,"ty":"sh","ix":1,"ks":{"a":0,"k":{"i":[[0,0],[0,0]],"o":[[0,0],[0,0]],"v":[[0.75,-80],[0.75,24]],"c":false},"ix":2},"nm":"路径 1","mn":"ADBE Vector Shape - Group","hd":false},{"ty":"st","c":{"a":1,"k":[{"i":{"x":[0.833],"y":[0.833]},"o":{"x":[0.167],"y":[0.167]},"t":52.484,"s":[0.790025889874,0.807454049587,0.828094363213,1],"e":[0.121568627656,0.843137264252,0.68235296011,1]},{"i":{"x":[0.833],"y":[0.833]},"o":{"x":[0.167],"y":[0.167]},"t":54.814,"s":[0.121568627656,0.843137264252,0.68235296011,1],"e":[0,0.709803938866,0.388235300779,1]},{"i":{"x":[0.833],"y":[0.833]},"o":{"x":[0.167],"y":[0.167]},"t":64.062,"s":[0,0.709803938866,0.388235300779,1],"e":[0.121568627656,0.843137264252,0.68235296011,1]},{"i":{"x":[0.833],"y":[0.833]},"o":{"x":[0.167],"y":[0.167]},"t":64.945,"s":[0.121568627656,0.843137264252,0.68235296011,1],"e":[0.790025889874,0.807454049587,0.828094363213,1]},{"t":66.9567036292853}],"ix":3},"o":{"a":0,"k":100,"ix":4},"w":{"a":0,"k":6,"ix":5},"lc":2,"lj":1,"ml":4,"bm":0,"nm":"描边 1","mn":"ADBE Vector Graphic - Stroke","hd":false},{"ty":"tm","s":{"a":1,"k":[{"i":{"x":[0.833],"y":[0.833]},"o":{"x":[0.167],"y":[0.167]},"t":52.484,"s":[60],"e":[42]},{"i":{"x":[0.833],"y":[0.833]},"o":{"x":[0.167],"y":[0.167]},"t":59.721,"s":[42],"e":[60]},{"t":66.9567036292853}],"ix":1},"e":{"a":0,"k":67,"ix":2},"o":{"a":0,"k":0,"ix":3},"m":1,"ix":3,"nm":"Trim Paths","mn":"ADBE Vector Filter - Trim","hd":false},{"ty":"tr","p":{"a":0,"k":[0,234],"ix":2},"a":{"a":0,"k":[0,234],"ix":1},"s":{"a":0,"k":[100,100],"ix":3},"r":{"a":0,"k":84,"ix":6},"o":{"a":0,"k":100,"ix":7},"sk":{"a":0,"k":0,"ix":4},"sa":{"a":0,"k":0,"ix":5},"nm":"Transform"}],"nm":"形状 15","np":3,"cix":2,"bm":0,"ix":15,"mn":"ADBE Vector Group","hd":false},{"ty":"gr","it":[{"ind":0,"ty":"sh","ix":1,"ks":{"a":0,"k":{"i":[[0,0],[0,0]],"o":[[0,0],[0,0]],"v":[[0.75,-80],[0.75,24]],"c":false},"ix":2},"nm":"路径 1","mn":"ADBE Vector Shape - Group","hd":false},{"ty":"st","c":{"a":1,"k":[{"i":{"x":[0.833],"y":[0.833]},"o":{"x":[0.167],"y":[0.167]},"t":53.67,"s":[0.790025889874,0.807454049587,0.828094363213,1],"e":[0.121568627656,0.843137264252,0.68235296011,1]},{"i":{"x":[0.833],"y":[0.833]},"o":{"x":[0.167],"y":[0.167]},"t":56.565,"s":[0.121568627656,0.843137264252,0.68235296011,1],"e":[0.121568627656,0.843137264252,0.68235296011,1]},{"i":{"x":[0.833],"y":[0.833]},"o":{"x":[0.167],"y":[0.167]},"t":65.249,"s":[0.121568627656,0.843137264252,0.68235296011,1],"e":[0.790025889874,0.807454049587,0.828094363213,1]},{"t":68.1427307064206}],"ix":3},"o":{"a":0,"k":100,"ix":4},"w":{"a":0,"k":6,"ix":5},"lc":2,"lj":1,"ml":4,"bm":0,"nm":"描边 1","mn":"ADBE Vector Graphic - Stroke","hd":false},{"ty":"tm","s":{"a":1,"k":[{"i":{"x":[0.833],"y":[0.833]},"o":{"x":[0.167],"y":[0.167]},"t":53.67,"s":[60],"e":[42]},{"i":{"x":[0.833],"y":[0.833]},"o":{"x":[0.167],"y":[0.167]},"t":60.907,"s":[42],"e":[60]},{"t":68.1427307064206}],"ix":1},"e":{"a":0,"k":67,"ix":2},"o":{"a":0,"k":0,"ix":3},"m":1,"ix":3,"nm":"Trim Paths","mn":"ADBE Vector Filter - Trim","hd":false},{"ty":"tr","p":{"a":0,"k":[0,234],"ix":2},"a":{"a":0,"k":[0,234],"ix":1},"s":{"a":0,"k":[100,100],"ix":3},"r":{"a":0,"k":90,"ix":6},"o":{"a":0,"k":100,"ix":7},"sk":{"a":0,"k":0,"ix":4},"sa":{"a":0,"k":0,"ix":5},"nm":"Transform"}],"nm":"形状 16","np":3,"cix":2,"bm":0,"ix":16,"mn":"ADBE Vector Group","hd":false},{"ty":"gr","it":[{"ind":0,"ty":"sh","ix":1,"ks":{"a":0,"k":{"i":[[0,0],[0,0]],"o":[[0,0],[0,0]],"v":[[0.75,-80],[0.75,24]],"c":false},"ix":2},"nm":"路径 1","mn":"ADBE Vector Shape - Group","hd":false},{"ty":"st","c":{"a":1,"k":[{"i":{"x":[0.833],"y":[0.833]},"o":{"x":[0.167],"y":[0.167]},"t":54.843,"s":[0.790025889874,0.807454049587,0.828094363213,1],"e":[0.121568627656,0.843137264252,0.68235296011,1]},{"i":{"x":[0.833],"y":[0.833]},"o":{"x":[0.167],"y":[0.167]},"t":57.708,"s":[0.121568627656,0.843137264252,0.68235296011,1],"e":[0.121568627656,0.843137264252,0.68235296011,1]},{"i":{"x":[0.833],"y":[0.833]},"o":{"x":[0.167],"y":[0.167]},"t":66.392,"s":[0.121568627656,0.843137264252,0.68235296011,1],"e":[0.790025889874,0.807454049587,0.828094363213,1]},{"t":69.314757463927}],"ix":3},"o":{"a":0,"k":100,"ix":4},"w":{"a":0,"k":6,"ix":5},"lc":2,"lj":1,"ml":4,"bm":0,"nm":"描边 1","mn":"ADBE Vector Graphic - Stroke","hd":false},{"ty":"tm","s":{"a":1,"k":[{"i":{"x":[0.833],"y":[0.833]},"o":{"x":[0.167],"y":[0.167]},"t":54.843,"s":[60],"e":[42]},{"i":{"x":[0.833],"y":[0.833]},"o":{"x":[0.167],"y":[0.167]},"t":62.079,"s":[42],"e":[60]},{"t":69.314757463927}],"ix":1},"e":{"a":0,"k":67,"ix":2},"o":{"a":0,"k":0,"ix":3},"m":1,"ix":3,"nm":"Trim Paths","mn":"ADBE Vector Filter - Trim","hd":false},{"ty":"tr","p":{"a":0,"k":[0,234],"ix":2},"a":{"a":0,"k":[0,234],"ix":1},"s":{"a":0,"k":[100,100],"ix":3},"r":{"a":0,"k":96,"ix":6},"o":{"a":0,"k":100,"ix":7},"sk":{"a":0,"k":0,"ix":4},"sa":{"a":0,"k":0,"ix":5},"nm":"Transform"}],"nm":"形状 17","np":3,"cix":2,"bm":0,"ix":17,"mn":"ADBE Vector Group","hd":false},{"ty":"gr","it":[{"ind":0,"ty":"sh","ix":1,"ks":{"a":0,"k":{"i":[[0,0],[0,0]],"o":[[0,0],[0,0]],"v":[[0.75,-80],[0.75,24]],"c":false},"ix":2},"nm":"路径 1","mn":"ADBE Vector Shape - Group","hd":false},{"ty":"st","c":{"a":1,"k":[{"i":{"x":[0.833],"y":[0.833]},"o":{"x":[0.167],"y":[0.167]},"t":56.015,"s":[0.790025889874,0.807454049587,0.828094363213,1],"e":[0.121568627656,0.843137264252,0.68235296011,1]},{"i":{"x":[0.833],"y":[0.833]},"o":{"x":[0.167],"y":[0.167]},"t":58.91,"s":[0.121568627656,0.843137264252,0.68235296011,1],"e":[0.121568627656,0.843137264252,0.68235296011,1]},{"i":{"x":[0.833],"y":[0.833]},"o":{"x":[0.167],"y":[0.167]},"t":67.839,"s":[0.121568627656,0.843137264252,0.68235296011,1],"e":[0.790025889874,0.807454049587,0.828094363213,1]},{"t":70.487784244264}],"ix":3},"o":{"a":0,"k":100,"ix":4},"w":{"a":0,"k":6,"ix":5},"lc":2,"lj":1,"ml":4,"bm":0,"nm":"描边 1","mn":"ADBE Vector Graphic - Stroke","hd":false},{"ty":"tm","s":{"a":1,"k":[{"i":{"x":[0.833],"y":[0.833]},"o":{"x":[0.167],"y":[0.167]},"t":56.015,"s":[60],"e":[42]},{"i":{"x":[0.833],"y":[0.833]},"o":{"x":[0.167],"y":[0.167]},"t":63.252,"s":[42],"e":[60]},{"t":70.487784244264}],"ix":1},"e":{"a":0,"k":67,"ix":2},"o":{"a":0,"k":0,"ix":3},"m":1,"ix":3,"nm":"Trim Paths","mn":"ADBE Vector Filter - Trim","hd":false},{"ty":"tr","p":{"a":0,"k":[0,234],"ix":2},"a":{"a":0,"k":[0,234],"ix":1},"s":{"a":0,"k":[100,100],"ix":3},"r":{"a":0,"k":102,"ix":6},"o":{"a":0,"k":100,"ix":7},"sk":{"a":0,"k":0,"ix":4},"sa":{"a":0,"k":0,"ix":5},"nm":"Transform"}],"nm":"形状 18","np":3,"cix":2,"bm":0,"ix":18,"mn":"ADBE Vector Group","hd":false},{"ty":"gr","it":[{"ind":0,"ty":"sh","ix":1,"ks":{"a":0,"k":{"i":[[0,0],[0,0]],"o":[[0,0],[0,0]],"v":[[0.75,-80],[0.75,24]],"c":false},"ix":2},"nm":"路径 1","mn":"ADBE Vector Shape - Group","hd":false},{"ty":"st","c":{"a":1,"k":[{"i":{"x":[0.833],"y":[0.833]},"o":{"x":[0.167],"y":[0.167]},"t":57.201,"s":[0.790025889874,0.807454049587,0.828094363213,1],"e":[0.121568627656,0.843137264252,0.68235296011,1]},{"i":{"x":[0.833],"y":[0.833]},"o":{"x":[0.167],"y":[0.167]},"t":60.603,"s":[0.121568627656,0.843137264252,0.68235296011,1],"e":[0.121568627656,0.843137264252,0.68235296011,1]},{"i":{"x":[0.833],"y":[0.833]},"o":{"x":[0.167],"y":[0.167]},"t":68.78,"s":[0.121568627656,0.843137264252,0.68235296011,1],"e":[0.790025889874,0.807454049587,0.828094363213,1]},{"t":71.6738113213993}],"ix":3},"o":{"a":0,"k":100,"ix":4},"w":{"a":0,"k":6,"ix":5},"lc":2,"lj":1,"ml":4,"bm":0,"nm":"描边 1","mn":"ADBE Vector Graphic - Stroke","hd":false},{"ty":"tm","s":{"a":1,"k":[{"i":{"x":[0.833],"y":[0.833]},"o":{"x":[0.167],"y":[0.167]},"t":57.201,"s":[60],"e":[42]},{"i":{"x":[0.833],"y":[0.833]},"o":{"x":[0.167],"y":[0.167]},"t":64.438,"s":[42],"e":[60]},{"t":71.6738113213993}],"ix":1},"e":{"a":0,"k":67,"ix":2},"o":{"a":0,"k":0,"ix":3},"m":1,"ix":3,"nm":"Trim Paths","mn":"ADBE Vector Filter - Trim","hd":false},{"ty":"tr","p":{"a":0,"k":[0,234],"ix":2},"a":{"a":0,"k":[0,234],"ix":1},"s":{"a":0,"k":[100,100],"ix":3},"r":{"a":0,"k":108,"ix":6},"o":{"a":0,"k":100,"ix":7},"sk":{"a":0,"k":0,"ix":4},"sa":{"a":0,"k":0,"ix":5},"nm":"Transform"}],"nm":"形状 19","np":3,"cix":2,"bm":0,"ix":19,"mn":"ADBE Vector Group","hd":false},{"ty":"gr","it":[{"ind":0,"ty":"sh","ix":1,"ks":{"a":0,"k":{"i":[[0,0],[0,0]],"o":[[0,0],[0,0]],"v":[[0.75,-80],[0.75,24]],"c":false},"ix":2},"nm":"路径 1","mn":"ADBE Vector Shape - Group","hd":false},{"ty":"st","c":{"a":1,"k":[{"i":{"x":[0.833],"y":[0.833]},"o":{"x":[0.167],"y":[0.167]},"t":58.375,"s":[0.790025889874,0.807454049587,0.828094363213,1],"e":[0.121568627656,0.843137264252,0.68235296011,1]},{"i":{"x":[0.833],"y":[0.833]},"o":{"x":[0.167],"y":[0.167]},"t":61.269,"s":[0.121568627656,0.843137264252,0.68235296011,1],"e":[0.121568627656,0.843137264252,0.68235296011,1]},{"i":{"x":[0.833],"y":[0.833]},"o":{"x":[0.167],"y":[0.167]},"t":69.287,"s":[0.121568627656,0.843137264252,0.68235296011,1],"e":[0.790025889874,0.807454049587,0.828094363213,1]},{"t":72.8468381017363}],"ix":3},"o":{"a":0,"k":100,"ix":4},"w":{"a":0,"k":6,"ix":5},"lc":2,"lj":1,"ml":4,"bm":0,"nm":"描边 1","mn":"ADBE Vector Graphic - Stroke","hd":false},{"ty":"tm","s":{"a":1,"k":[{"i":{"x":[0.833],"y":[0.833]},"o":{"x":[0.167],"y":[0.167]},"t":58.375,"s":[60],"e":[42]},{"i":{"x":[0.833],"y":[0.833]},"o":{"x":[0.167],"y":[0.167]},"t":65.611,"s":[42],"e":[60]},{"t":72.8468381017363}],"ix":1},"e":{"a":0,"k":67,"ix":2},"o":{"a":0,"k":0,"ix":3},"m":1,"ix":3,"nm":"Trim Paths","mn":"ADBE Vector Filter - Trim","hd":false},{"ty":"tr","p":{"a":0,"k":[0,234],"ix":2},"a":{"a":0,"k":[0,234],"ix":1},"s":{"a":0,"k":[100,100],"ix":3},"r":{"a":0,"k":114,"ix":6},"o":{"a":0,"k":100,"ix":7},"sk":{"a":0,"k":0,"ix":4},"sa":{"a":0,"k":0,"ix":5},"nm":"Transform"}],"nm":"形状 20","np":3,"cix":2,"bm":0,"ix":20,"mn":"ADBE Vector Group","hd":false},{"ty":"gr","it":[{"ind":0,"ty":"sh","ix":1,"ks":{"a":0,"k":{"i":[[0,0],[0,0]],"o":[[0,0],[0,0]],"v":[[0.75,-80],[0.75,24]],"c":false},"ix":2},"nm":"路径 1","mn":"ADBE Vector Shape - Group","hd":false},{"ty":"st","c":{"a":1,"k":[{"i":{"x":[0.833],"y":[0.833]},"o":{"x":[0.167],"y":[0.167]},"t":59.547,"s":[0.790025889874,0.807454049587,0.828094363213,1],"e":[0.121568627656,0.843137264252,0.68235296011,1]},{"i":{"x":[0.833],"y":[0.833]},"o":{"x":[0.167],"y":[0.167]},"t":62.051,"s":[0.121568627656,0.843137264252,0.68235296011,1],"e":[0.121568627656,0.843137264252,0.68235296011,1]},{"i":{"x":[0.833],"y":[0.833]},"o":{"x":[0.167],"y":[0.167]},"t":70.734,"s":[0.121568627656,0.843137264252,0.68235296011,1],"e":[0.790025889874,0.807454049587,0.828094363213,1]},{"t":74.0188648592427}],"ix":3},"o":{"a":0,"k":100,"ix":4},"w":{"a":0,"k":6,"ix":5},"lc":2,"lj":1,"ml":4,"bm":0,"nm":"描边 1","mn":"ADBE Vector Graphic - Stroke","hd":false},{"ty":"tm","s":{"a":1,"k":[{"i":{"x":[0.833],"y":[0.833]},"o":{"x":[0.167],"y":[0.167]},"t":59.547,"s":[60],"e":[42]},{"i":{"x":[0.833],"y":[0.833]},"o":{"x":[0.167],"y":[0.167]},"t":66.783,"s":[42],"e":[60]},{"t":74.0188648592427}],"ix":1},"e":{"a":0,"k":67,"ix":2},"o":{"a":0,"k":0,"ix":3},"m":1,"ix":3,"nm":"Trim Paths","mn":"ADBE Vector Filter - Trim","hd":false},{"ty":"tr","p":{"a":0,"k":[0,234],"ix":2},"a":{"a":0,"k":[0,234],"ix":1},"s":{"a":0,"k":[100,100],"ix":3},"r":{"a":0,"k":120,"ix":6},"o":{"a":0,"k":100,"ix":7},"sk":{"a":0,"k":0,"ix":4},"sa":{"a":0,"k":0,"ix":5},"nm":"Transform"}],"nm":"形状 21","np":3,"cix":2,"bm":0,"ix":21,"mn":"ADBE Vector Group","hd":false},{"ty":"gr","it":[{"ind":0,"ty":"sh","ix":1,"ks":{"a":0,"k":{"i":[[0,0],[0,0]],"o":[[0,0],[0,0]],"v":[[0.75,-80],[0.75,24]],"c":false},"ix":2},"nm":"路径 1","mn":"ADBE Vector Shape - Group","hd":false},{"ty":"st","c":{"a":1,"k":[{"i":{"x":[0.833],"y":[0.833]},"o":{"x":[0.167],"y":[0.167]},"t":60.734,"s":[0.790025889874,0.807454049587,0.828094363213,1],"e":[0.121568627656,0.843137264252,0.68235296011,1]},{"i":{"x":[0.833],"y":[0.833]},"o":{"x":[0.167],"y":[0.167]},"t":63.498,"s":[0.121568627656,0.843137264252,0.68235296011,1],"e":[0.121568627656,0.843137264252,0.68235296011,1]},{"i":{"x":[0.833],"y":[0.833]},"o":{"x":[0.167],"y":[0.167]},"t":72.181,"s":[0.121568627656,0.843137264252,0.68235296011,1],"e":[0.790025889874,0.807454049587,0.828094363213,1]},{"t":75.2058919592086}],"ix":3},"o":{"a":0,"k":100,"ix":4},"w":{"a":0,"k":6,"ix":5},"lc":2,"lj":1,"ml":4,"bm":0,"nm":"描边 1","mn":"ADBE Vector Graphic - Stroke","hd":false},{"ty":"tm","s":{"a":1,"k":[{"i":{"x":[0.833],"y":[0.833]},"o":{"x":[0.167],"y":[0.167]},"t":60.734,"s":[60],"e":[42]},{"i":{"x":[0.833],"y":[0.833]},"o":{"x":[0.167],"y":[0.167]},"t":67.97,"s":[42],"e":[60]},{"t":75.2058919592086}],"ix":1},"e":{"a":0,"k":67,"ix":2},"o":{"a":0,"k":0,"ix":3},"m":1,"ix":3,"nm":"Trim Paths","mn":"ADBE Vector Filter - Trim","hd":false},{"ty":"tr","p":{"a":0,"k":[0,234],"ix":2},"a":{"a":0,"k":[0,234],"ix":1},"s":{"a":0,"k":[100,100],"ix":3},"r":{"a":0,"k":126,"ix":6},"o":{"a":0,"k":100,"ix":7},"sk":{"a":0,"k":0,"ix":4},"sa":{"a":0,"k":0,"ix":5},"nm":"Transform"}],"nm":"形状 22","np":3,"cix":2,"bm":0,"ix":22,"mn":"ADBE Vector Group","hd":false},{"ty":"gr","it":[{"ind":0,"ty":"sh","ix":1,"ks":{"a":0,"k":{"i":[[0,0],[0,0]],"o":[[0,0],[0,0]],"v":[[0.75,-80],[0.75,24]],"c":false},"ix":2},"nm":"路径 1","mn":"ADBE Vector Shape - Group","hd":false},{"ty":"st","c":{"a":1,"k":[{"i":{"x":[0.833],"y":[0.833]},"o":{"x":[0.167],"y":[0.167]},"t":61.906,"s":[0.790025889874,0.807454049587,0.828094363213,1],"e":[0.121568627656,0.843137264252,0.68235296011,1]},{"i":{"x":[0.833],"y":[0.833]},"o":{"x":[0.167],"y":[0.167]},"t":64.945,"s":[0.121568627656,0.843137264252,0.68235296011,1],"e":[0.121568627656,0.843137264252,0.68235296011,1]},{"i":{"x":[0.833],"y":[0.833]},"o":{"x":[0.167],"y":[0.167]},"t":73.628,"s":[0.121568627656,0.843137264252,0.68235296011,1],"e":[0.790025889874,0.807454049587,0.828094363213,1]},{"t":76.377918716715}],"ix":3},"o":{"a":0,"k":100,"ix":4},"w":{"a":0,"k":6,"ix":5},"lc":2,"lj":1,"ml":4,"bm":0,"nm":"描边 1","mn":"ADBE Vector Graphic - Stroke","hd":false},{"ty":"tm","s":{"a":1,"k":[{"i":{"x":[0.833],"y":[0.833]},"o":{"x":[0.167],"y":[0.167]},"t":61.906,"s":[60],"e":[42]},{"i":{"x":[0.833],"y":[0.833]},"o":{"x":[0.167],"y":[0.167]},"t":69.142,"s":[42],"e":[60]},{"t":76.377918716715}],"ix":1},"e":{"a":0,"k":67,"ix":2},"o":{"a":0,"k":0,"ix":3},"m":1,"ix":3,"nm":"Trim Paths","mn":"ADBE Vector Filter - Trim","hd":false},{"ty":"tr","p":{"a":0,"k":[0,234],"ix":2},"a":{"a":0,"k":[0,234],"ix":1},"s":{"a":0,"k":[100,100],"ix":3},"r":{"a":0,"k":132,"ix":6},"o":{"a":0,"k":100,"ix":7},"sk":{"a":0,"k":0,"ix":4},"sa":{"a":0,"k":0,"ix":5},"nm":"Transform"}],"nm":"形状 23","np":3,"cix":2,"bm":0,"ix":23,"mn":"ADBE Vector Group","hd":false},{"ty":"gr","it":[{"ind":0,"ty":"sh","ix":1,"ks":{"a":0,"k":{"i":[[0,0],[0,0]],"o":[[0,0],[0,0]],"v":[[0.75,-80],[0.75,24]],"c":false},"ix":2},"nm":"路径 1","mn":"ADBE Vector Shape - Group","hd":false},{"ty":"st","c":{"a":1,"k":[{"i":{"x":[0.833],"y":[0.833]},"o":{"x":[0.167],"y":[0.167]},"t":63.078,"s":[0.790025889874,0.807454049587,0.828094363213,1],"e":[0.121568627656,0.843137264252,0.68235296011,1]},{"i":{"x":[0.833],"y":[0.833]},"o":{"x":[0.167],"y":[0.167]},"t":65.972,"s":[0.121568627656,0.843137264252,0.68235296011,1],"e":[0.121568627656,0.843137264252,0.68235296011,1]},{"i":{"x":[0.833],"y":[0.833]},"o":{"x":[0.167],"y":[0.167]},"t":74.656,"s":[0.121568627656,0.843137264252,0.68235296011,1],"e":[0.790025889874,0.807454049587,0.828094363213,1]},{"t":77.5499454742214}],"ix":3},"o":{"a":0,"k":100,"ix":4},"w":{"a":0,"k":6,"ix":5},"lc":2,"lj":1,"ml":4,"bm":0,"nm":"描边 1","mn":"ADBE Vector Graphic - Stroke","hd":false},{"ty":"tm","s":{"a":1,"k":[{"i":{"x":[0.833],"y":[0.833]},"o":{"x":[0.167],"y":[0.167]},"t":63.078,"s":[60],"e":[42]},{"i":{"x":[0.833],"y":[0.833]},"o":{"x":[0.167],"y":[0.167]},"t":70.314,"s":[42],"e":[60]},{"t":77.5499454742214}],"ix":1},"e":{"a":0,"k":67,"ix":2},"o":{"a":0,"k":0,"ix":3},"m":1,"ix":3,"nm":"Trim Paths","mn":"ADBE Vector Filter - Trim","hd":false},{"ty":"tr","p":{"a":0,"k":[0,234],"ix":2},"a":{"a":0,"k":[0,234],"ix":1},"s":{"a":0,"k":[100,100],"ix":3},"r":{"a":0,"k":138,"ix":6},"o":{"a":0,"k":100,"ix":7},"sk":{"a":0,"k":0,"ix":4},"sa":{"a":0,"k":0,"ix":5},"nm":"Transform"}],"nm":"形状 24","np":3,"cix":2,"bm":0,"ix":24,"mn":"ADBE Vector Group","hd":false},{"ty":"gr","it":[{"ind":0,"ty":"sh","ix":1,"ks":{"a":0,"k":{"i":[[0,0],[0,0]],"o":[[0,0],[0,0]],"v":[[0.75,-80],[0.75,24]],"c":false},"ix":2},"nm":"路径 1","mn":"ADBE Vector Shape - Group","hd":false},{"ty":"st","c":{"a":1,"k":[{"i":{"x":[0.833],"y":[0.833]},"o":{"x":[0.167],"y":[0.167]},"t":64.265,"s":[0.790025889874,0.807454049587,0.828094363213,1],"e":[0.121568627656,0.843137264252,0.68235296011,1]},{"i":{"x":[0.833],"y":[0.833]},"o":{"x":[0.167],"y":[0.167]},"t":67.159,"s":[0.121568627656,0.843137264252,0.68235296011,1],"e":[0.121568627656,0.843137264252,0.68235296011,1]},{"i":{"x":[0.833],"y":[0.833]},"o":{"x":[0.167],"y":[0.167]},"t":75.842,"s":[0.121568627656,0.843137264252,0.68235296011,1],"e":[0.790025889874,0.807454049587,0.828094363213,1]},{"t":78.7369725741873}],"ix":3},"o":{"a":0,"k":100,"ix":4},"w":{"a":0,"k":6,"ix":5},"lc":2,"lj":1,"ml":4,"bm":0,"nm":"描边 1","mn":"ADBE Vector Graphic - Stroke","hd":false},{"ty":"tm","s":{"a":1,"k":[{"i":{"x":[0.833],"y":[0.833]},"o":{"x":[0.167],"y":[0.167]},"t":64.265,"s":[60],"e":[42]},{"i":{"x":[0.833],"y":[0.833]},"o":{"x":[0.167],"y":[0.167]},"t":71.501,"s":[42],"e":[60]},{"t":78.7369725741873}],"ix":1},"e":{"a":0,"k":67,"ix":2},"o":{"a":0,"k":0,"ix":3},"m":1,"ix":3,"nm":"Trim Paths","mn":"ADBE Vector Filter - Trim","hd":false},{"ty":"tr","p":{"a":0,"k":[0,234],"ix":2},"a":{"a":0,"k":[0,234],"ix":1},"s":{"a":0,"k":[100,100],"ix":3},"r":{"a":0,"k":144,"ix":6},"o":{"a":0,"k":100,"ix":7},"sk":{"a":0,"k":0,"ix":4},"sa":{"a":0,"k":0,"ix":5},"nm":"Transform"}],"nm":"形状 25","np":3,"cix":2,"bm":0,"ix":25,"mn":"ADBE Vector Group","hd":false},{"ty":"gr","it":[{"ind":0,"ty":"sh","ix":1,"ks":{"a":0,"k":{"i":[[0,0],[0,0]],"o":[[0,0],[0,0]],"v":[[0.75,-80],[0.75,24]],"c":false},"ix":2},"nm":"路径 1","mn":"ADBE Vector Shape - Group","hd":false},{"ty":"st","c":{"a":1,"k":[{"i":{"x":[0.833],"y":[0.833]},"o":{"x":[0.167],"y":[0.167]},"t":65.437,"s":[0.790025889874,0.807454049587,0.828094363213,1],"e":[0.121568627656,0.843137264252,0.68235296011,1]},{"i":{"x":[0.833],"y":[0.833]},"o":{"x":[0.167],"y":[0.167]},"t":68.331,"s":[0.121568627656,0.843137264252,0.68235296011,1],"e":[0.121568627656,0.843137264252,0.68235296011,1]},{"i":{"x":[0.833],"y":[0.833]},"o":{"x":[0.167],"y":[0.167]},"t":77.015,"s":[0.121568627656,0.843137264252,0.68235296011,1],"e":[0.790025889874,0.807454049587,0.828094363213,1]},{"t":79.9089993316937}],"ix":3},"o":{"a":0,"k":100,"ix":4},"w":{"a":0,"k":6,"ix":5},"lc":2,"lj":1,"ml":4,"bm":0,"nm":"描边 1","mn":"ADBE Vector Graphic - Stroke","hd":false},{"ty":"tm","s":{"a":1,"k":[{"i":{"x":[0.833],"y":[0.833]},"o":{"x":[0.167],"y":[0.167]},"t":65.437,"s":[60],"e":[42]},{"i":{"x":[0.833],"y":[0.833]},"o":{"x":[0.167],"y":[0.167]},"t":72.673,"s":[42],"e":[60]},{"t":79.9089993316937}],"ix":1},"e":{"a":0,"k":67,"ix":2},"o":{"a":0,"k":0,"ix":3},"m":1,"ix":3,"nm":"Trim Paths","mn":"ADBE Vector Filter - Trim","hd":false},{"ty":"tr","p":{"a":0,"k":[0,234],"ix":2},"a":{"a":0,"k":[0,234],"ix":1},"s":{"a":0,"k":[100,100],"ix":3},"r":{"a":0,"k":150,"ix":6},"o":{"a":0,"k":100,"ix":7},"sk":{"a":0,"k":0,"ix":4},"sa":{"a":0,"k":0,"ix":5},"nm":"Transform"}],"nm":"形状 26","np":3,"cix":2,"bm":0,"ix":26,"mn":"ADBE Vector Group","hd":false},{"ty":"gr","it":[{"ind":0,"ty":"sh","ix":1,"ks":{"a":0,"k":{"i":[[0,0],[0,0]],"o":[[0,0],[0,0]],"v":[[0.75,-80],[0.75,24]],"c":false},"ix":2},"nm":"路径 1","mn":"ADBE Vector Shape - Group","hd":false},{"ty":"st","c":{"a":1,"k":[{"i":{"x":[0.833],"y":[0.833]},"o":{"x":[0.167],"y":[0.167]},"t":66.609,"s":[0.790025889874,0.807454049587,0.828094363213,1],"e":[0.121568627656,0.843137264252,0.68235296011,1]},{"i":{"x":[0.833],"y":[0.833]},"o":{"x":[0.167],"y":[0.167]},"t":69.504,"s":[0.121568627656,0.843137264252,0.68235296011,1],"e":[0.121568627656,0.843137264252,0.68235296011,1]},{"i":{"x":[0.833],"y":[0.833]},"o":{"x":[0.167],"y":[0.167]},"t":78.187,"s":[0.121568627656,0.843137264252,0.68235296011,1],"e":[0.790025889874,0.807454049587,0.828094363213,1]},{"t":81.0810260892001}],"ix":3},"o":{"a":0,"k":100,"ix":4},"w":{"a":0,"k":6,"ix":5},"lc":2,"lj":1,"ml":4,"bm":0,"nm":"描边 1","mn":"ADBE Vector Graphic - Stroke","hd":false},{"ty":"tm","s":{"a":1,"k":[{"i":{"x":[0.833],"y":[0.833]},"o":{"x":[0.167],"y":[0.167]},"t":66.609,"s":[60],"e":[42]},{"i":{"x":[0.833],"y":[0.833]},"o":{"x":[0.167],"y":[0.167]},"t":73.845,"s":[42],"e":[60]},{"t":81.0810260892001}],"ix":1},"e":{"a":0,"k":67,"ix":2},"o":{"a":0,"k":0,"ix":3},"m":1,"ix":3,"nm":"Trim Paths","mn":"ADBE Vector Filter - Trim","hd":false},{"ty":"tr","p":{"a":0,"k":[0,234],"ix":2},"a":{"a":0,"k":[0,234],"ix":1},"s":{"a":0,"k":[100,100],"ix":3},"r":{"a":0,"k":156,"ix":6},"o":{"a":0,"k":100,"ix":7},"sk":{"a":0,"k":0,"ix":4},"sa":{"a":0,"k":0,"ix":5},"nm":"Transform"}],"nm":"形状 27","np":3,"cix":2,"bm":0,"ix":27,"mn":"ADBE Vector Group","hd":false},{"ty":"gr","it":[{"ind":0,"ty":"sh","ix":1,"ks":{"a":0,"k":{"i":[[0,0],[0,0]],"o":[[0,0],[0,0]],"v":[[0.75,-80],[0.75,24]],"c":false},"ix":2},"nm":"路径 1","mn":"ADBE Vector Shape - Group","hd":false},{"ty":"st","c":{"a":1,"k":[{"i":{"x":[0.833],"y":[0.833]},"o":{"x":[0.167],"y":[0.167]},"t":67.796,"s":[0.790025889874,0.807454049587,0.828094363213,1],"e":[0.121568627656,0.843137264252,0.68235296011,1]},{"i":{"x":[0.833],"y":[0.833]},"o":{"x":[0.167],"y":[0.167]},"t":70.69,"s":[0.121568627656,0.843137264252,0.68235296011,1],"e":[0.121568627656,0.843137264252,0.68235296011,1]},{"i":{"x":[0.833],"y":[0.833]},"o":{"x":[0.167],"y":[0.167]},"t":79.374,"s":[0.121568627656,0.843137264252,0.68235296011,1],"e":[0.790025889874,0.807454049587,0.828094363213,1]},{"t":82.268053189166}],"ix":3},"o":{"a":0,"k":100,"ix":4},"w":{"a":0,"k":6,"ix":5},"lc":2,"lj":1,"ml":4,"bm":0,"nm":"描边 1","mn":"ADBE Vector Graphic - Stroke","hd":false},{"ty":"tm","s":{"a":1,"k":[{"i":{"x":[0.833],"y":[0.833]},"o":{"x":[0.167],"y":[0.167]},"t":67.796,"s":[60],"e":[42]},{"i":{"x":[0.833],"y":[0.833]},"o":{"x":[0.167],"y":[0.167]},"t":75.032,"s":[42],"e":[60]},{"t":82.268053189166}],"ix":1},"e":{"a":0,"k":67,"ix":2},"o":{"a":0,"k":0,"ix":3},"m":1,"ix":3,"nm":"Trim Paths","mn":"ADBE Vector Filter - Trim","hd":false},{"ty":"tr","p":{"a":0,"k":[0,234],"ix":2},"a":{"a":0,"k":[0,234],"ix":1},"s":{"a":0,"k":[100,100],"ix":3},"r":{"a":0,"k":162,"ix":6},"o":{"a":0,"k":100,"ix":7},"sk":{"a":0,"k":0,"ix":4},"sa":{"a":0,"k":0,"ix":5},"nm":"Transform"}],"nm":"形状 28","np":3,"cix":2,"bm":0,"ix":28,"mn":"ADBE Vector Group","hd":false},{"ty":"gr","it":[{"ind":0,"ty":"sh","ix":1,"ks":{"a":0,"k":{"i":[[0,0],[0,0]],"o":[[0,0],[0,0]],"v":[[0.75,-80],[0.75,24]],"c":false},"ix":2},"nm":"路径 1","mn":"ADBE Vector Shape - Group","hd":false},{"ty":"st","c":{"a":1,"k":[{"i":{"x":[0.833],"y":[0.833]},"o":{"x":[0.167],"y":[0.167]},"t":68.968,"s":[0.790025889874,0.807454049587,0.828094363213,1],"e":[0.121568627656,0.843137264252,0.68235296011,1]},{"i":{"x":[0.833],"y":[0.833]},"o":{"x":[0.167],"y":[0.167]},"t":71.863,"s":[0.121568627656,0.843137264252,0.68235296011,1],"e":[0.121568627656,0.843137264252,0.68235296011,1]},{"i":{"x":[0.833],"y":[0.833]},"o":{"x":[0.167],"y":[0.167]},"t":80.546,"s":[0.121568627656,0.843137264252,0.68235296011,1],"e":[0.790025889874,0.807454049587,0.828094363213,1]},{"t":83.4400799466724}],"ix":3},"o":{"a":0,"k":100,"ix":4},"w":{"a":0,"k":6,"ix":5},"lc":2,"lj":1,"ml":4,"bm":0,"nm":"描边 1","mn":"ADBE Vector Graphic - Stroke","hd":false},{"ty":"tm","s":{"a":1,"k":[{"i":{"x":[0.833],"y":[0.833]},"o":{"x":[0.167],"y":[0.167]},"t":68.968,"s":[60],"e":[42]},{"i":{"x":[0.833],"y":[0.833]},"o":{"x":[0.167],"y":[0.167]},"t":76.204,"s":[42],"e":[60]},{"t":83.4400799466724}],"ix":1},"e":{"a":0,"k":67,"ix":2},"o":{"a":0,"k":0,"ix":3},"m":1,"ix":3,"nm":"Trim Paths","mn":"ADBE Vector Filter - Trim","hd":false},{"ty":"tr","p":{"a":0,"k":[0,234],"ix":2},"a":{"a":0,"k":[0,234],"ix":1},"s":{"a":0,"k":[100,100],"ix":3},"r":{"a":0,"k":168,"ix":6},"o":{"a":0,"k":100,"ix":7},"sk":{"a":0,"k":0,"ix":4},"sa":{"a":0,"k":0,"ix":5},"nm":"Transform"}],"nm":"形状 29","np":3,"cix":2,"bm":0,"ix":29,"mn":"ADBE Vector Group","hd":false},{"ty":"gr","it":[{"ind":0,"ty":"sh","ix":1,"ks":{"a":0,"k":{"i":[[0,0],[0,0]],"o":[[0,0],[0,0]],"v":[[0.75,-80],[0.75,24]],"c":false},"ix":2},"nm":"路径 1","mn":"ADBE Vector Shape - Group","hd":false},{"ty":"st","c":{"a":1,"k":[{"i":{"x":[0.833],"y":[0.833]},"o":{"x":[0.167],"y":[0.167]},"t":70.14,"s":[0.790025889874,0.807454049587,0.828094363213,1],"e":[0.121568627656,0.843137264252,0.68235296011,1]},{"i":{"x":[0.833],"y":[0.833]},"o":{"x":[0.167],"y":[0.167]},"t":73.035,"s":[0.121568627656,0.843137264252,0.68235296011,1],"e":[0.121568627656,0.843137264252,0.68235296011,1]},{"i":{"x":[0.833],"y":[0.833]},"o":{"x":[0.167],"y":[0.167]},"t":81.718,"s":[0.121568627656,0.843137264252,0.68235296011,1],"e":[0.790025889874,0.807454049587,0.828094363213,1]},{"t":84.6121067041788}],"ix":3},"o":{"a":0,"k":100,"ix":4},"w":{"a":0,"k":6,"ix":5},"lc":2,"lj":1,"ml":4,"bm":0,"nm":"描边 1","mn":"ADBE Vector Graphic - Stroke","hd":false},{"ty":"tm","s":{"a":1,"k":[{"i":{"x":[0.833],"y":[0.833]},"o":{"x":[0.167],"y":[0.167]},"t":70.14,"s":[60],"e":[42]},{"i":{"x":[0.833],"y":[0.833]},"o":{"x":[0.167],"y":[0.167]},"t":77.376,"s":[42],"e":[60]},{"t":84.6121067041788}],"ix":1},"e":{"a":0,"k":67,"ix":2},"o":{"a":0,"k":0,"ix":3},"m":1,"ix":3,"nm":"Trim Paths","mn":"ADBE Vector Filter - Trim","hd":false},{"ty":"tr","p":{"a":0,"k":[0,234],"ix":2},"a":{"a":0,"k":[0,234],"ix":1},"s":{"a":0,"k":[100,100],"ix":3},"r":{"a":0,"k":174,"ix":6},"o":{"a":0,"k":100,"ix":7},"sk":{"a":0,"k":0,"ix":4},"sa":{"a":0,"k":0,"ix":5},"nm":"Transform"}],"nm":"形状 30","np":3,"cix":2,"bm":0,"ix":30,"mn":"ADBE Vector Group","hd":false},{"ty":"gr","it":[{"ind":0,"ty":"sh","ix":1,"ks":{"a":0,"k":{"i":[[0,0],[0,0]],"o":[[0,0],[0,0]],"v":[[0.75,-80],[0.75,24]],"c":false},"ix":2},"nm":"路径 1","mn":"ADBE Vector Shape - Group","hd":false},{"ty":"st","c":{"a":1,"k":[{"i":{"x":[0.833],"y":[0.833]},"o":{"x":[0.167],"y":[0.167]},"t":71.327,"s":[0.790025889874,0.807454049587,0.828094363213,1],"e":[0.121568627656,0.843137264252,0.68235296011,1]},{"i":{"x":[0.833],"y":[0.833]},"o":{"x":[0.167],"y":[0.167]},"t":74.221,"s":[0.121568627656,0.843137264252,0.68235296011,1],"e":[0.121568627656,0.843137264252,0.68235296011,1]},{"i":{"x":[0.833],"y":[0.833]},"o":{"x":[0.167],"y":[0.167]},"t":82.905,"s":[0.121568627656,0.843137264252,0.68235296011,1],"e":[0.790025889874,0.807454049587,0.828094363213,1]},{"t":85.7991338041447}],"ix":3},"o":{"a":0,"k":100,"ix":4},"w":{"a":0,"k":6,"ix":5},"lc":2,"lj":1,"ml":4,"bm":0,"nm":"描边 1","mn":"ADBE Vector Graphic - Stroke","hd":false},{"ty":"tm","s":{"a":1,"k":[{"i":{"x":[0.833],"y":[0.833]},"o":{"x":[0.167],"y":[0.167]},"t":71.327,"s":[60],"e":[42]},{"i":{"x":[0.833],"y":[0.833]},"o":{"x":[0.167],"y":[0.167]},"t":78.563,"s":[42],"e":[60]},{"t":85.7991338041447}],"ix":1},"e":{"a":0,"k":67,"ix":2},"o":{"a":0,"k":0,"ix":3},"m":1,"ix":3,"nm":"Trim Paths","mn":"ADBE Vector Filter - Trim","hd":false},{"ty":"tr","p":{"a":0,"k":[0,234],"ix":2},"a":{"a":0,"k":[0,234],"ix":1},"s":{"a":0,"k":[100,100],"ix":3},"r":{"a":0,"k":180,"ix":6},"o":{"a":0,"k":100,"ix":7},"sk":{"a":0,"k":0,"ix":4},"sa":{"a":0,"k":0,"ix":5},"nm":"Transform"}],"nm":"形状 31","np":3,"cix":2,"bm":0,"ix":31,"mn":"ADBE Vector Group","hd":false},{"ty":"gr","it":[{"ind":0,"ty":"sh","ix":1,"ks":{"a":0,"k":{"i":[[0,0],[0,0]],"o":[[0,0],[0,0]],"v":[[0.75,-80],[0.75,24]],"c":false},"ix":2},"nm":"路径 1","mn":"ADBE Vector Shape - Group","hd":false},{"ty":"st","c":{"a":1,"k":[{"i":{"x":[0.833],"y":[0.833]},"o":{"x":[0.167],"y":[0.167]},"t":72.499,"s":[0.790025889874,0.807454049587,0.828094363213,1],"e":[0.121568627656,0.843137264252,0.68235296011,1]},{"i":{"x":[0.833],"y":[0.833]},"o":{"x":[0.167],"y":[0.167]},"t":75.394,"s":[0.121568627656,0.843137264252,0.68235296011,1],"e":[0.121568627656,0.843137264252,0.68235296011,1]},{"i":{"x":[0.833],"y":[0.833]},"o":{"x":[0.167],"y":[0.167]},"t":83.759,"s":[0.121568627656,0.843137264252,0.68235296011,1],"e":[0.790025889874,0.807454049587,0.828094363213,1]},{"t":86.9711605616511}],"ix":3},"o":{"a":0,"k":100,"ix":4},"w":{"a":0,"k":6,"ix":5},"lc":2,"lj":1,"ml":4,"bm":0,"nm":"描边 1","mn":"ADBE Vector Graphic - Stroke","hd":false},{"ty":"tm","s":{"a":1,"k":[{"i":{"x":[0.833],"y":[0.833]},"o":{"x":[0.167],"y":[0.167]},"t":72.499,"s":[60],"e":[42]},{"i":{"x":[0.833],"y":[0.833]},"o":{"x":[0.167],"y":[0.167]},"t":79.735,"s":[42],"e":[60]},{"t":86.9711605616511}],"ix":1},"e":{"a":0,"k":67,"ix":2},"o":{"a":0,"k":0,"ix":3},"m":1,"ix":3,"nm":"Trim Paths","mn":"ADBE Vector Filter - Trim","hd":false},{"ty":"tr","p":{"a":0,"k":[0,234],"ix":2},"a":{"a":0,"k":[0,234],"ix":1},"s":{"a":0,"k":[100,100],"ix":3},"r":{"a":0,"k":186,"ix":6},"o":{"a":0,"k":100,"ix":7},"sk":{"a":0,"k":0,"ix":4},"sa":{"a":0,"k":0,"ix":5},"nm":"Transform"}],"nm":"形状 32","np":3,"cix":2,"bm":0,"ix":32,"mn":"ADBE Vector Group","hd":false},{"ty":"gr","it":[{"ind":0,"ty":"sh","ix":1,"ks":{"a":0,"k":{"i":[[0,0],[0,0]],"o":[[0,0],[0,0]],"v":[[0.75,-80],[0.75,24]],"c":false},"ix":2},"nm":"路径 1","mn":"ADBE Vector Shape - Group","hd":false},{"ty":"st","c":{"a":1,"k":[{"i":{"x":[0.833],"y":[0.833]},"o":{"x":[0.167],"y":[0.167]},"t":73.672,"s":[0.790025889874,0.807454049587,0.828094363213,1],"e":[0.121568627656,0.843137264252,0.68235296011,1]},{"i":{"x":[0.833],"y":[0.833]},"o":{"x":[0.167],"y":[0.167]},"t":76.523,"s":[0.121568627656,0.843137264252,0.68235296011,1],"e":[0.121568627656,0.843137264252,0.68235296011,1]},{"i":{"x":[0.833],"y":[0.833]},"o":{"x":[0.167],"y":[0.167]},"t":85.206,"s":[0.121568627656,0.843137264252,0.68235296011,1],"e":[0.790025889874,0.807454049587,0.828094363213,1]},{"t":88.1441873419881}],"ix":3},"o":{"a":0,"k":100,"ix":4},"w":{"a":0,"k":6,"ix":5},"lc":2,"lj":1,"ml":4,"bm":0,"nm":"描边 1","mn":"ADBE Vector Graphic - Stroke","hd":false},{"ty":"tm","s":{"a":1,"k":[{"i":{"x":[0.833],"y":[0.833]},"o":{"x":[0.167],"y":[0.167]},"t":73.672,"s":[60],"e":[42]},{"i":{"x":[0.833],"y":[0.833]},"o":{"x":[0.167],"y":[0.167]},"t":80.908,"s":[42],"e":[60]},{"t":88.1441873419881}],"ix":1},"e":{"a":0,"k":67,"ix":2},"o":{"a":0,"k":0,"ix":3},"m":1,"ix":3,"nm":"Trim Paths","mn":"ADBE Vector Filter - Trim","hd":false},{"ty":"tr","p":{"a":0,"k":[0,234],"ix":2},"a":{"a":0,"k":[0,234],"ix":1},"s":{"a":0,"k":[100,100],"ix":3},"r":{"a":0,"k":192,"ix":6},"o":{"a":0,"k":100,"ix":7},"sk":{"a":0,"k":0,"ix":4},"sa":{"a":0,"k":0,"ix":5},"nm":"Transform"}],"nm":"形状 33","np":3,"cix":2,"bm":0,"ix":33,"mn":"ADBE Vector Group","hd":false},{"ty":"gr","it":[{"ind":0,"ty":"sh","ix":1,"ks":{"a":0,"k":{"i":[[0,0],[0,0]],"o":[[0,0],[0,0]],"v":[[0.75,-80],[0.75,24]],"c":false},"ix":2},"nm":"路径 1","mn":"ADBE Vector Shape - Group","hd":false},{"ty":"st","c":{"a":1,"k":[{"i":{"x":[0.833],"y":[0.833]},"o":{"x":[0.167],"y":[0.167]},"t":74.858,"s":[0.790025889874,0.807454049587,0.828094363213,1],"e":[0.121568627656,0.843137264252,0.68235296011,1]},{"i":{"x":[0.833],"y":[0.833]},"o":{"x":[0.167],"y":[0.167]},"t":77.753,"s":[0.121568627656,0.843137264252,0.68235296011,1],"e":[0.121568627656,0.843137264252,0.68235296011,1]},{"i":{"x":[0.833],"y":[0.833]},"o":{"x":[0.167],"y":[0.167]},"t":86.653,"s":[0.121568627656,0.843137264252,0.68235296011,1],"e":[0.790025889874,0.807454049587,0.828094363213,1]},{"t":89.3302144191234}],"ix":3},"o":{"a":0,"k":100,"ix":4},"w":{"a":0,"k":6,"ix":5},"lc":2,"lj":1,"ml":4,"bm":0,"nm":"描边 1","mn":"ADBE Vector Graphic - Stroke","hd":false},{"ty":"tm","s":{"a":1,"k":[{"i":{"x":[0.833],"y":[0.833]},"o":{"x":[0.167],"y":[0.167]},"t":74.858,"s":[60],"e":[42]},{"i":{"x":[0.833],"y":[0.833]},"o":{"x":[0.167],"y":[0.167]},"t":82.094,"s":[42],"e":[60]},{"t":89.3302144191234}],"ix":1},"e":{"a":0,"k":67,"ix":2},"o":{"a":0,"k":0,"ix":3},"m":1,"ix":3,"nm":"Trim Paths","mn":"ADBE Vector Filter - Trim","hd":false},{"ty":"tr","p":{"a":0,"k":[0,234],"ix":2},"a":{"a":0,"k":[0,234],"ix":1},"s":{"a":0,"k":[100,100],"ix":3},"r":{"a":0,"k":198,"ix":6},"o":{"a":0,"k":100,"ix":7},"sk":{"a":0,"k":0,"ix":4},"sa":{"a":0,"k":0,"ix":5},"nm":"Transform"}],"nm":"形状 34","np":3,"cix":2,"bm":0,"ix":34,"mn":"ADBE Vector Group","hd":false},{"ty":"gr","it":[{"ind":0,"ty":"sh","ix":1,"ks":{"a":0,"k":{"i":[[0,0],[0,0]],"o":[[0,0],[0,0]],"v":[[0.75,-80],[0.75,24]],"c":false},"ix":2},"nm":"路径 1","mn":"ADBE Vector Shape - Group","hd":false},{"ty":"st","c":{"a":1,"k":[{"i":{"x":[0.833],"y":[0.833]},"o":{"x":[0.167],"y":[0.167]},"t":76.03,"s":[0.790025889874,0.807454049587,0.828094363213,1],"e":[0.121568627656,0.843137264252,0.68235296011,1]},{"i":{"x":[0.833],"y":[0.833]},"o":{"x":[0.167],"y":[0.167]},"t":78.925,"s":[0.121568627656,0.843137264252,0.68235296011,1],"e":[0.121568627656,0.843137264252,0.68235296011,1]},{"i":{"x":[0.833],"y":[0.833]},"o":{"x":[0.167],"y":[0.167]},"t":87.608,"s":[0.121568627656,0.843137264252,0.68235296011,1],"e":[0.790025889874,0.807454049587,0.828094363213,1]},{"t":90.5022411766298}],"ix":3},"o":{"a":0,"k":100,"ix":4},"w":{"a":0,"k":6,"ix":5},"lc":2,"lj":1,"ml":4,"bm":0,"nm":"描边 1","mn":"ADBE Vector Graphic - Stroke","hd":false},{"ty":"tm","s":{"a":1,"k":[{"i":{"x":[0.833],"y":[0.833]},"o":{"x":[0.167],"y":[0.167]},"t":76.03,"s":[60],"e":[42]},{"i":{"x":[0.833],"y":[0.833]},"o":{"x":[0.167],"y":[0.167]},"t":83.266,"s":[42],"e":[60]},{"t":90.5022411766298}],"ix":1},"e":{"a":0,"k":67,"ix":2},"o":{"a":0,"k":0,"ix":3},"m":1,"ix":3,"nm":"Trim Paths","mn":"ADBE Vector Filter - Trim","hd":false},{"ty":"tr","p":{"a":0,"k":[0,234],"ix":2},"a":{"a":0,"k":[0,234],"ix":1},"s":{"a":0,"k":[100,100],"ix":3},"r":{"a":0,"k":204,"ix":6},"o":{"a":0,"k":100,"ix":7},"sk":{"a":0,"k":0,"ix":4},"sa":{"a":0,"k":0,"ix":5},"nm":"Transform"}],"nm":"形状 35","np":3,"cix":2,"bm":0,"ix":35,"mn":"ADBE Vector Group","hd":false},{"ty":"gr","it":[{"ind":0,"ty":"sh","ix":1,"ks":{"a":0,"k":{"i":[[0,0],[0,0]],"o":[[0,0],[0,0]],"v":[[0.75,-80],[0.75,24]],"c":false},"ix":2},"nm":"路径 1","mn":"ADBE Vector Shape - Group","hd":false},{"ty":"st","c":{"a":1,"k":[{"i":{"x":[0.833],"y":[0.833]},"o":{"x":[0.167],"y":[0.167]},"t":77.203,"s":[0.790025889874,0.807454049587,0.828094363213,1],"e":[0,0.709803938866,0.388235300779,1]},{"i":{"x":[0.833],"y":[0.833]},"o":{"x":[0.167],"y":[0.167]},"t":80.097,"s":[0,0.709803938866,0.388235300779,1],"e":[0.121568627656,0.843137264252,0.68235296011,1]},{"i":{"x":[0.833],"y":[0.833]},"o":{"x":[0.167],"y":[0.167]},"t":80.864,"s":[0.121568627656,0.843137264252,0.68235296011,1],"e":[0.121568627656,0.843137264252,0.68235296011,1]},{"i":{"x":[0.833],"y":[0.833]},"o":{"x":[0.167],"y":[0.167]},"t":88.78,"s":[0.121568627656,0.843137264252,0.68235296011,1],"e":[0.790025889874,0.807454049587,0.828094363213,1]},{"t":91.6752679569668}],"ix":3},"o":{"a":0,"k":100,"ix":4},"w":{"a":0,"k":6,"ix":5},"lc":2,"lj":1,"ml":4,"bm":0,"nm":"描边 1","mn":"ADBE Vector Graphic - Stroke","hd":false},{"ty":"tm","s":{"a":1,"k":[{"i":{"x":[0.833],"y":[0.833]},"o":{"x":[0.167],"y":[0.167]},"t":77.203,"s":[60],"e":[42]},{"i":{"x":[0.833],"y":[0.833]},"o":{"x":[0.167],"y":[0.167]},"t":84.439,"s":[42],"e":[60]},{"t":91.6752679569668}],"ix":1},"e":{"a":0,"k":67,"ix":2},"o":{"a":0,"k":0,"ix":3},"m":1,"ix":3,"nm":"Trim Paths","mn":"ADBE Vector Filter - Trim","hd":false},{"ty":"tr","p":{"a":0,"k":[0,234],"ix":2},"a":{"a":0,"k":[0,234],"ix":1},"s":{"a":0,"k":[100,100],"ix":3},"r":{"a":0,"k":210,"ix":6},"o":{"a":0,"k":100,"ix":7},"sk":{"a":0,"k":0,"ix":4},"sa":{"a":0,"k":0,"ix":5},"nm":"Transform"}],"nm":"形状 36","np":3,"cix":2,"bm":0,"ix":36,"mn":"ADBE Vector Group","hd":false},{"ty":"gr","it":[{"ind":0,"ty":"sh","ix":1,"ks":{"a":0,"k":{"i":[[0,0],[0,0]],"o":[[0,0],[0,0]],"v":[[0.75,-80],[0.75,24]],"c":false},"ix":2},"nm":"路径 1","mn":"ADBE Vector Shape - Group","hd":false},{"ty":"st","c":{"a":1,"k":[{"i":{"x":[0.833],"y":[0.833]},"o":{"x":[0.167],"y":[0.167]},"t":78.389,"s":[0.790025889874,0.807454049587,0.828094363213,1],"e":[0.121568627656,0.843137264252,0.68235296011,1]},{"i":{"x":[0.833],"y":[0.833]},"o":{"x":[0.167],"y":[0.167]},"t":81.284,"s":[0.121568627656,0.843137264252,0.68235296011,1],"e":[0.121568627656,0.843137264252,0.68235296011,1]},{"i":{"x":[0.833],"y":[0.833]},"o":{"x":[0.167],"y":[0.167]},"t":89.967,"s":[0.121568627656,0.843137264252,0.68235296011,1],"e":[0.790025889874,0.807454049587,0.828094363213,1]},{"t":92.8612956696961}],"ix":3},"o":{"a":0,"k":100,"ix":4},"w":{"a":0,"k":6,"ix":5},"lc":2,"lj":1,"ml":4,"bm":0,"nm":"描边 1","mn":"ADBE Vector Graphic - Stroke","hd":false},{"ty":"tm","s":{"a":1,"k":[{"i":{"x":[0.833],"y":[0.833]},"o":{"x":[0.167],"y":[0.167]},"t":78.389,"s":[60],"e":[42]},{"i":{"x":[0.833],"y":[0.833]},"o":{"x":[0.167],"y":[0.167]},"t":85.625,"s":[42],"e":[60]},{"t":92.8612956696961}],"ix":1},"e":{"a":0,"k":67,"ix":2},"o":{"a":0,"k":0,"ix":3},"m":1,"ix":3,"nm":"Trim Paths","mn":"ADBE Vector Filter - Trim","hd":false},{"ty":"tr","p":{"a":0,"k":[0,234],"ix":2},"a":{"a":0,"k":[0,234],"ix":1},"s":{"a":0,"k":[100,100],"ix":3},"r":{"a":0,"k":216,"ix":6},"o":{"a":0,"k":100,"ix":7},"sk":{"a":0,"k":0,"ix":4},"sa":{"a":0,"k":0,"ix":5},"nm":"Transform"}],"nm":"形状 37","np":3,"cix":2,"bm":0,"ix":37,"mn":"ADBE Vector Group","hd":false},{"ty":"gr","it":[{"ind":0,"ty":"sh","ix":1,"ks":{"a":0,"k":{"i":[[0,0],[0,0]],"o":[[0,0],[0,0]],"v":[[0.75,-80],[0.75,24]],"c":false},"ix":2},"nm":"路径 1","mn":"ADBE Vector Shape - Group","hd":false},{"ty":"st","c":{"a":1,"k":[{"i":{"x":[0.833],"y":[0.833]},"o":{"x":[0.167],"y":[0.167]},"t":79.562,"s":[0.790025889874,0.807454049587,0.828094363213,1],"e":[0.121568627656,0.843137264252,0.68235296011,1]},{"i":{"x":[0.833],"y":[0.833]},"o":{"x":[0.167],"y":[0.167]},"t":82.311,"s":[0.121568627656,0.843137264252,0.68235296011,1],"e":[0.121568627656,0.843137264252,0.68235296011,1]},{"i":{"x":[0.833],"y":[0.833]},"o":{"x":[0.167],"y":[0.167]},"t":90.994,"s":[0.121568627656,0.843137264252,0.68235296011,1],"e":[0.790025889874,0.807454049587,0.828094363213,1]},{"t":94.0343195206515}],"ix":3},"o":{"a":0,"k":100,"ix":4},"w":{"a":0,"k":6,"ix":5},"lc":2,"lj":1,"ml":4,"bm":0,"nm":"描边 1","mn":"ADBE Vector Graphic - Stroke","hd":false},{"ty":"tm","s":{"a":1,"k":[{"i":{"x":[0.833],"y":[0.833]},"o":{"x":[0.167],"y":[0.167]},"t":79.562,"s":[60],"e":[42]},{"i":{"x":[0.833],"y":[0.833]},"o":{"x":[0.167],"y":[0.167]},"t":86.798,"s":[42],"e":[60]},{"t":94.0343195206515}],"ix":1},"e":{"a":0,"k":67,"ix":2},"o":{"a":0,"k":0,"ix":3},"m":1,"ix":3,"nm":"Trim Paths","mn":"ADBE Vector Filter - Trim","hd":false},{"ty":"tr","p":{"a":0,"k":[0,234],"ix":2},"a":{"a":0,"k":[0,234],"ix":1},"s":{"a":0,"k":[100,100],"ix":3},"r":{"a":0,"k":222,"ix":6},"o":{"a":0,"k":100,"ix":7},"sk":{"a":0,"k":0,"ix":4},"sa":{"a":0,"k":0,"ix":5},"nm":"Transform"}],"nm":"形状 38","np":3,"cix":2,"bm":0,"ix":38,"mn":"ADBE Vector Group","hd":false},{"ty":"gr","it":[{"ind":0,"ty":"sh","ix":1,"ks":{"a":0,"k":{"i":[[0,0],[0,0]],"o":[[0,0],[0,0]],"v":[[0.75,-80],[0.75,24]],"c":false},"ix":2},"nm":"路径 1","mn":"ADBE Vector Shape - Group","hd":false},{"ty":"st","c":{"a":1,"k":[{"i":{"x":[0.833],"y":[0.833]},"o":{"x":[0.167],"y":[0.167]},"t":80.734,"s":[0.790025889874,0.807454049587,0.828094363213,1],"e":[0.121568627656,0.843137264252,0.68235296011,1]},{"i":{"x":[0.833],"y":[0.833]},"o":{"x":[0.167],"y":[0.167]},"t":83.759,"s":[0.121568627656,0.843137264252,0.68235296011,1],"e":[0.121568627656,0.843137264252,0.68235296011,1]},{"i":{"x":[0.833],"y":[0.833]},"o":{"x":[0.167],"y":[0.167]},"t":92.442,"s":[0.121568627656,0.843137264252,0.68235296011,1],"e":[0.790025889874,0.807454049587,0.828094363213,1]},{"t":95.2063485719455}],"ix":3},"o":{"a":0,"k":100,"ix":4},"w":{"a":0,"k":6,"ix":5},"lc":2,"lj":1,"ml":4,"bm":0,"nm":"描边 1","mn":"ADBE Vector Graphic - Stroke","hd":false},{"ty":"tm","s":{"a":1,"k":[{"i":{"x":[0.833],"y":[0.833]},"o":{"x":[0.167],"y":[0.167]},"t":80.734,"s":[60],"e":[42]},{"i":{"x":[0.833],"y":[0.833]},"o":{"x":[0.167],"y":[0.167]},"t":87.97,"s":[42],"e":[60]},{"t":95.2063485719455}],"ix":1},"e":{"a":0,"k":67,"ix":2},"o":{"a":0,"k":0,"ix":3},"m":1,"ix":3,"nm":"Trim Paths","mn":"ADBE Vector Filter - Trim","hd":false},{"ty":"tr","p":{"a":0,"k":[0,234],"ix":2},"a":{"a":0,"k":[0,234],"ix":1},"s":{"a":0,"k":[100,100],"ix":3},"r":{"a":0,"k":228,"ix":6},"o":{"a":0,"k":100,"ix":7},"sk":{"a":0,"k":0,"ix":4},"sa":{"a":0,"k":0,"ix":5},"nm":"Transform"}],"nm":"形状 39","np":3,"cix":2,"bm":0,"ix":39,"mn":"ADBE Vector Group","hd":false},{"ty":"gr","it":[{"ind":0,"ty":"sh","ix":1,"ks":{"a":0,"k":{"i":[[0,0],[0,0]],"o":[[0,0],[0,0]],"v":[[0.75,-80],[0.75,24]],"c":false},"ix":2},"nm":"路径 1","mn":"ADBE Vector Shape - Group","hd":false},{"ty":"st","c":{"a":1,"k":[{"i":{"x":[0.833],"y":[0.833]},"o":{"x":[0.167],"y":[0.167]},"t":81.921,"s":[0.790025889874,0.807454049587,0.828094363213,1],"e":[0.121568627656,0.843137264252,0.68235296011,1]},{"i":{"x":[0.833],"y":[0.833]},"o":{"x":[0.167],"y":[0.167]},"t":84.815,"s":[0.121568627656,0.843137264252,0.68235296011,1],"e":[0.121568627656,0.843137264252,0.68235296011,1]},{"i":{"x":[0.833],"y":[0.833]},"o":{"x":[0.167],"y":[0.167]},"t":93.889,"s":[0.121568627656,0.843137264252,0.68235296011,1],"e":[0.790025889874,0.807454049587,0.828094363213,1]},{"t":96.3933775745245}],"ix":3},"o":{"a":0,"k":100,"ix":4},"w":{"a":0,"k":6,"ix":5},"lc":2,"lj":1,"ml":4,"bm":0,"nm":"描边 1","mn":"ADBE Vector Graphic - Stroke","hd":false},{"ty":"tm","s":{"a":1,"k":[{"i":{"x":[0.833],"y":[0.833]},"o":{"x":[0.167],"y":[0.167]},"t":81.921,"s":[60],"e":[42]},{"i":{"x":[0.833],"y":[0.833]},"o":{"x":[0.167],"y":[0.167]},"t":89.157,"s":[42],"e":[60]},{"t":96.3933775745245}],"ix":1},"e":{"a":0,"k":67,"ix":2},"o":{"a":0,"k":0,"ix":3},"m":1,"ix":3,"nm":"Trim Paths","mn":"ADBE Vector Filter - Trim","hd":false},{"ty":"tr","p":{"a":0,"k":[0,234],"ix":2},"a":{"a":0,"k":[0,234],"ix":1},"s":{"a":0,"k":[100,100],"ix":3},"r":{"a":0,"k":234,"ix":6},"o":{"a":0,"k":100,"ix":7},"sk":{"a":0,"k":0,"ix":4},"sa":{"a":0,"k":0,"ix":5},"nm":"Transform"}],"nm":"形状 40","np":3,"cix":2,"bm":0,"ix":40,"mn":"ADBE Vector Group","hd":false},{"ty":"gr","it":[{"ind":0,"ty":"sh","ix":1,"ks":{"a":0,"k":{"i":[[0,0],[0,0]],"o":[[0,0],[0,0]],"v":[[0.75,-80],[0.75,24]],"c":false},"ix":2},"nm":"路径 1","mn":"ADBE Vector Shape - Group","hd":false},{"ty":"st","c":{"a":1,"k":[{"i":{"x":[0.833],"y":[0.833]},"o":{"x":[0.167],"y":[0.167]},"t":83.093,"s":[0.790025889874,0.807454049587,0.828094363213,1],"e":[0.121568627656,0.843137264252,0.68235296011,1]},{"i":{"x":[0.833],"y":[0.833]},"o":{"x":[0.167],"y":[0.167]},"t":86.653,"s":[0.121568627656,0.843137264252,0.68235296011,1],"e":[0.121568627656,0.843137264252,0.68235296011,1]},{"i":{"x":[0.833],"y":[0.833]},"o":{"x":[0.167],"y":[0.167]},"t":94.67,"s":[0.121568627656,0.843137264252,0.68235296011,1],"e":[0.790025889874,0.807454049587,0.828094363213,1]},{"t":97.5654067852156}],"ix":3},"o":{"a":0,"k":100,"ix":4},"w":{"a":0,"k":6,"ix":5},"lc":2,"lj":1,"ml":4,"bm":0,"nm":"描边 1","mn":"ADBE Vector Graphic - Stroke","hd":false},{"ty":"tm","s":{"a":1,"k":[{"i":{"x":[0.833],"y":[0.833]},"o":{"x":[0.167],"y":[0.167]},"t":83.093,"s":[60],"e":[42]},{"i":{"x":[0.833],"y":[0.833]},"o":{"x":[0.167],"y":[0.167]},"t":90.329,"s":[42],"e":[60]},{"t":97.5654067852156}],"ix":1},"e":{"a":0,"k":67,"ix":2},"o":{"a":0,"k":0,"ix":3},"m":1,"ix":3,"nm":"Trim Paths","mn":"ADBE Vector Filter - Trim","hd":false},{"ty":"tr","p":{"a":0,"k":[0,234],"ix":2},"a":{"a":0,"k":[0,234],"ix":1},"s":{"a":0,"k":[100,100],"ix":3},"r":{"a":0,"k":240,"ix":6},"o":{"a":0,"k":100,"ix":7},"sk":{"a":0,"k":0,"ix":4},"sa":{"a":0,"k":0,"ix":5},"nm":"Transform"}],"nm":"形状 41","np":3,"cix":2,"bm":0,"ix":41,"mn":"ADBE Vector Group","hd":false},{"ty":"gr","it":[{"ind":0,"ty":"sh","ix":1,"ks":{"a":0,"k":{"i":[[0,0],[0,0]],"o":[[0,0],[0,0]],"v":[[0.75,-80],[0.75,24]],"c":false},"ix":2},"nm":"路径 1","mn":"ADBE Vector Shape - Group","hd":false},{"ty":"st","c":{"a":1,"k":[{"i":{"x":[0.833],"y":[0.833]},"o":{"x":[0.167],"y":[0.167]},"t":84.265,"s":[0.790025889874,0.807454049587,0.828094363213,1],"e":[0.121568627656,0.843137264252,0.68235296011,1]},{"i":{"x":[0.833],"y":[0.833]},"o":{"x":[0.167],"y":[0.167]},"t":86.653,"s":[0.121568627656,0.843137264252,0.68235296011,1],"e":[0.121568627656,0.843137264252,0.68235296011,1]},{"i":{"x":[0.833],"y":[0.833]},"o":{"x":[0.167],"y":[0.167]},"t":95.336,"s":[0.121568627656,0.843137264252,0.68235296011,1],"e":[0.790025889874,0.807454049587,0.828094363213,1]},{"t":98.7374291869242}],"ix":3},"o":{"a":0,"k":100,"ix":4},"w":{"a":0,"k":6,"ix":5},"lc":2,"lj":1,"ml":4,"bm":0,"nm":"描边 1","mn":"ADBE Vector Graphic - Stroke","hd":false},{"ty":"tm","s":{"a":1,"k":[{"i":{"x":[0.833],"y":[0.833]},"o":{"x":[0.167],"y":[0.167]},"t":84.265,"s":[60],"e":[42]},{"i":{"x":[0.833],"y":[0.833]},"o":{"x":[0.167],"y":[0.167]},"t":91.501,"s":[42],"e":[60]},{"t":98.7374291869242}],"ix":1},"e":{"a":0,"k":67,"ix":2},"o":{"a":0,"k":0,"ix":3},"m":1,"ix":3,"nm":"Trim Paths","mn":"ADBE Vector Filter - Trim","hd":false},{"ty":"tr","p":{"a":0,"k":[0,234],"ix":2},"a":{"a":0,"k":[0,234],"ix":1},"s":{"a":0,"k":[100,100],"ix":3},"r":{"a":0,"k":246,"ix":6},"o":{"a":0,"k":100,"ix":7},"sk":{"a":0,"k":0,"ix":4},"sa":{"a":0,"k":0,"ix":5},"nm":"Transform"}],"nm":"形状 42","np":3,"cix":2,"bm":0,"ix":42,"mn":"ADBE Vector Group","hd":false},{"ty":"gr","it":[{"ind":0,"ty":"sh","ix":1,"ks":{"a":0,"k":{"i":[[0,0],[0,0]],"o":[[0,0],[0,0]],"v":[[0.75,-80],[0.75,24]],"c":false},"ix":2},"nm":"路径 1","mn":"ADBE Vector Shape - Group","hd":false},{"ty":"st","c":{"a":1,"k":[{"i":{"x":[0.833],"y":[0.833]},"o":{"x":[0.167],"y":[0.167]},"t":85.452,"s":[0.790025889874,0.807454049587,0.828094363213,1],"e":[0.121568627656,0.843137264252,0.68235296011,1]},{"i":{"x":[0.833],"y":[0.833]},"o":{"x":[0.167],"y":[0.167]},"t":88.1,"s":[0.121568627656,0.843137264252,0.68235296011,1],"e":[0.121568627656,0.843137264252,0.68235296011,1]},{"i":{"x":[0.833],"y":[0.833]},"o":{"x":[0.167],"y":[0.167]},"t":96.783,"s":[0.121568627656,0.843137264252,0.68235296011,1],"e":[0.790025889874,0.807454049587,0.828094363213,1]},{"t":99.9244534064419}],"ix":3},"o":{"a":0,"k":100,"ix":4},"w":{"a":0,"k":6,"ix":5},"lc":2,"lj":1,"ml":4,"bm":0,"nm":"描边 1","mn":"ADBE Vector Graphic - Stroke","hd":false},{"ty":"tm","s":{"a":1,"k":[{"i":{"x":[0.833],"y":[0.833]},"o":{"x":[0.167],"y":[0.167]},"t":85.452,"s":[60],"e":[42]},{"i":{"x":[0.833],"y":[0.833]},"o":{"x":[0.167],"y":[0.167]},"t":92.688,"s":[42],"e":[60]},{"t":99.9244534064419}],"ix":1},"e":{"a":0,"k":67,"ix":2},"o":{"a":0,"k":0,"ix":3},"m":1,"ix":3,"nm":"Trim Paths","mn":"ADBE Vector Filter - Trim","hd":false},{"ty":"tr","p":{"a":0,"k":[0,234],"ix":2},"a":{"a":0,"k":[0,234],"ix":1},"s":{"a":0,"k":[100,100],"ix":3},"r":{"a":0,"k":252,"ix":6},"o":{"a":0,"k":100,"ix":7},"sk":{"a":0,"k":0,"ix":4},"sa":{"a":0,"k":0,"ix":5},"nm":"Transform"}],"nm":"形状 43","np":3,"cix":2,"bm":0,"ix":43,"mn":"ADBE Vector Group","hd":false},{"ty":"gr","it":[{"ind":0,"ty":"sh","ix":1,"ks":{"a":0,"k":{"i":[[0,0],[0,0]],"o":[[0,0],[0,0]],"v":[[0.75,-80],[0.75,24]],"c":false},"ix":2},"nm":"路径 1","mn":"ADBE Vector Shape - Group","hd":false},{"ty":"st","c":{"a":1,"k":[{"i":{"x":[0.833],"y":[0.833]},"o":{"x":[0.167],"y":[0.167]},"t":86.624,"s":[0.790025889874,0.807454049587,0.828094363213,1],"e":[0.121568627656,0.843137264252,0.68235296011,1]},{"i":{"x":[0.833],"y":[0.833]},"o":{"x":[0.167],"y":[0.167]},"t":89.547,"s":[0.121568627656,0.843137264252,0.68235296011,1],"e":[0.121568627656,0.843137264252,0.68235296011,1]},{"i":{"x":[0.833],"y":[0.833]},"o":{"x":[0.167],"y":[0.167]},"t":98.23,"s":[0.121568627656,0.843137264252,0.68235296011,1],"e":[0.790025889874,0.807454049587,0.828094363213,1]},{"t":101.096482617133}],"ix":3},"o":{"a":0,"k":100,"ix":4},"w":{"a":0,"k":6,"ix":5},"lc":2,"lj":1,"ml":4,"bm":0,"nm":"描边 1","mn":"ADBE Vector Graphic - Stroke","hd":false},{"ty":"tm","s":{"a":1,"k":[{"i":{"x":[0.833],"y":[0.833]},"o":{"x":[0.167],"y":[0.167]},"t":86.624,"s":[60],"e":[42]},{"i":{"x":[0.833],"y":[0.833]},"o":{"x":[0.167],"y":[0.167]},"t":93.86,"s":[42],"e":[60]},{"t":101.096482617133}],"ix":1},"e":{"a":0,"k":67,"ix":2},"o":{"a":0,"k":0,"ix":3},"m":1,"ix":3,"nm":"Trim Paths","mn":"ADBE Vector Filter - Trim","hd":false},{"ty":"tr","p":{"a":0,"k":[0,234],"ix":2},"a":{"a":0,"k":[0,234],"ix":1},"s":{"a":0,"k":[100,100],"ix":3},"r":{"a":0,"k":258,"ix":6},"o":{"a":0,"k":100,"ix":7},"sk":{"a":0,"k":0,"ix":4},"sa":{"a":0,"k":0,"ix":5},"nm":"Transform"}],"nm":"形状 44","np":3,"cix":2,"bm":0,"ix":44,"mn":"ADBE Vector Group","hd":false},{"ty":"gr","it":[{"ind":0,"ty":"sh","ix":1,"ks":{"a":0,"k":{"i":[[0,0],[0,0]],"o":[[0,0],[0,0]],"v":[[0.75,-80],[0.75,24]],"c":false},"ix":2},"nm":"路径 1","mn":"ADBE Vector Shape - Group","hd":false},{"ty":"st","c":{"a":1,"k":[{"i":{"x":[0.833],"y":[0.833]},"o":{"x":[0.167],"y":[0.167]},"t":87.796,"s":[0.790025889874,0.807454049587,0.828094363213,1],"e":[0.121568627656,0.843137264252,0.68235296011,1]},{"i":{"x":[0.833],"y":[0.833]},"o":{"x":[0.167],"y":[0.167]},"t":90.994,"s":[0.121568627656,0.843137264252,0.68235296011,1],"e":[0.121568627656,0.843137264252,0.68235296011,1]},{"i":{"x":[0.833],"y":[0.833]},"o":{"x":[0.167],"y":[0.167]},"t":99.678,"s":[0.121568627656,0.843137264252,0.68235296011,1],"e":[0.790025889874,0.807454049587,0.828094363213,1]},{"t":102.268509801903}],"ix":3},"o":{"a":0,"k":100,"ix":4},"w":{"a":0,"k":6,"ix":5},"lc":2,"lj":1,"ml":4,"bm":0,"nm":"描边 1","mn":"ADBE Vector Graphic - Stroke","hd":false},{"ty":"tm","s":{"a":1,"k":[{"i":{"x":[0.833],"y":[0.833]},"o":{"x":[0.167],"y":[0.167]},"t":87.796,"s":[60],"e":[42]},{"i":{"x":[0.833],"y":[0.833]},"o":{"x":[0.167],"y":[0.167]},"t":95.032,"s":[42],"e":[60]},{"t":102.268509801903}],"ix":1},"e":{"a":0,"k":67,"ix":2},"o":{"a":0,"k":0,"ix":3},"m":1,"ix":3,"nm":"Trim Paths","mn":"ADBE Vector Filter - Trim","hd":false},{"ty":"tr","p":{"a":0,"k":[0,234],"ix":2},"a":{"a":0,"k":[0,234],"ix":1},"s":{"a":0,"k":[100,100],"ix":3},"r":{"a":0,"k":264,"ix":6},"o":{"a":0,"k":100,"ix":7},"sk":{"a":0,"k":0,"ix":4},"sa":{"a":0,"k":0,"ix":5},"nm":"Transform"}],"nm":"形状 45","np":3,"cix":2,"bm":0,"ix":45,"mn":"ADBE Vector Group","hd":false},{"ty":"gr","it":[{"ind":0,"ty":"sh","ix":1,"ks":{"a":0,"k":{"i":[[0,0],[0,0]],"o":[[0,0],[0,0]],"v":[[0.75,-80],[0.75,24]],"c":false},"ix":2},"nm":"路径 1","mn":"ADBE Vector Shape - Group","hd":false},{"ty":"st","c":{"a":1,"k":[{"i":{"x":[0.833],"y":[0.833]},"o":{"x":[0.167],"y":[0.167]},"t":88.983,"s":[0.790025889874,0.807454049587,0.828094363213,1],"e":[0.121568627656,0.843137264252,0.68235296011,1]},{"i":{"x":[0.833],"y":[0.833]},"o":{"x":[0.167],"y":[0.167]},"t":92.442,"s":[0.121568627656,0.843137264252,0.68235296011,1],"e":[0.121568627656,0.843137264252,0.68235296011,1]},{"i":{"x":[0.833],"y":[0.833]},"o":{"x":[0.167],"y":[0.167]},"t":99.678,"s":[0.121568627656,0.843137264252,0.68235296011,1],"e":[0,0.709803938866,0.388235300779,1]},{"i":{"x":[0.833],"y":[0.833]},"o":{"x":[0.167],"y":[0.167]},"t":100.56,"s":[0,0.709803938866,0.388235300779,1],"e":[0.790025889874,0.807454049587,0.828094363213,1]},{"t":103.455539263383}],"ix":3},"o":{"a":0,"k":100,"ix":4},"w":{"a":0,"k":6,"ix":5},"lc":2,"lj":1,"ml":4,"bm":0,"nm":"描边 1","mn":"ADBE Vector Graphic - Stroke","hd":false},{"ty":"tm","s":{"a":1,"k":[{"i":{"x":[0.833],"y":[0.833]},"o":{"x":[0.167],"y":[0.167]},"t":88.983,"s":[60],"e":[42]},{"i":{"x":[0.833],"y":[0.833]},"o":{"x":[0.167],"y":[0.167]},"t":96.219,"s":[42],"e":[60]},{"t":103.455539263383}],"ix":1},"e":{"a":0,"k":67,"ix":2},"o":{"a":0,"k":0,"ix":3},"m":1,"ix":3,"nm":"Trim Paths","mn":"ADBE Vector Filter - Trim","hd":false},{"ty":"tr","p":{"a":0,"k":[0,234],"ix":2},"a":{"a":0,"k":[0,234],"ix":1},"s":{"a":0,"k":[100,100],"ix":3},"r":{"a":0,"k":270,"ix":6},"o":{"a":0,"k":100,"ix":7},"sk":{"a":0,"k":0,"ix":4},"sa":{"a":0,"k":0,"ix":5},"nm":"Transform"}],"nm":"形状 46","np":3,"cix":2,"bm":0,"ix":46,"mn":"ADBE Vector Group","hd":false},{"ty":"gr","it":[{"ind":0,"ty":"sh","ix":1,"ks":{"a":0,"k":{"i":[[0,0],[0,0]],"o":[[0,0],[0,0]],"v":[[0.75,-80],[0.75,24]],"c":false},"ix":2},"nm":"路径 1","mn":"ADBE Vector Shape - Group","hd":false},{"ty":"st","c":{"a":1,"k":[{"i":{"x":[0.833],"y":[0.833]},"o":{"x":[0.167],"y":[0.167]},"t":90.155,"s":[0.790025889874,0.807454049587,0.828094363213,1],"e":[0.121568627656,0.843137264252,0.68235296011,1]},{"i":{"x":[0.833],"y":[0.833]},"o":{"x":[0.167],"y":[0.167]},"t":92.442,"s":[0.121568627656,0.843137264252,0.68235296011,1],"e":[0.121568627656,0.843137264252,0.68235296011,1]},{"i":{"x":[0.833],"y":[0.833]},"o":{"x":[0.167],"y":[0.167]},"t":101.125,"s":[0.121568627656,0.843137264252,0.68235296011,1],"e":[0.790025889874,0.807454049587,0.828094363213,1]},{"t":104.62755844905}],"ix":3},"o":{"a":0,"k":100,"ix":4},"w":{"a":0,"k":6,"ix":5},"lc":2,"lj":1,"ml":4,"bm":0,"nm":"描边 1","mn":"ADBE Vector Graphic - Stroke","hd":false},{"ty":"tm","s":{"a":1,"k":[{"i":{"x":[0.833],"y":[0.833]},"o":{"x":[0.167],"y":[0.167]},"t":90.155,"s":[60],"e":[42]},{"i":{"x":[0.833],"y":[0.833]},"o":{"x":[0.167],"y":[0.167]},"t":97.391,"s":[42],"e":[60]},{"t":104.62755844905}],"ix":1},"e":{"a":0,"k":67,"ix":2},"o":{"a":0,"k":0,"ix":3},"m":1,"ix":3,"nm":"Trim Paths","mn":"ADBE Vector Filter - Trim","hd":false},{"ty":"tr","p":{"a":0,"k":[0,234],"ix":2},"a":{"a":0,"k":[0,234],"ix":1},"s":{"a":0,"k":[100,100],"ix":3},"r":{"a":0,"k":276,"ix":6},"o":{"a":0,"k":100,"ix":7},"sk":{"a":0,"k":0,"ix":4},"sa":{"a":0,"k":0,"ix":5},"nm":"Transform"}],"nm":"形状 47","np":3,"cix":2,"bm":0,"ix":47,"mn":"ADBE Vector Group","hd":false},{"ty":"gr","it":[{"ind":0,"ty":"sh","ix":1,"ks":{"a":0,"k":{"i":[[0,0],[0,0]],"o":[[0,0],[0,0]],"v":[[0.75,-80],[0.75,24]],"c":false},"ix":2},"nm":"路径 1","mn":"ADBE Vector Shape - Group","hd":false},{"ty":"st","c":{"a":1,"k":[{"i":{"x":[0.833],"y":[0.833]},"o":{"x":[0.167],"y":[0.167]},"t":91.327,"s":[0.790025889874,0.807454049587,0.828094363213,1],"e":[0.121568627656,0.843137264252,0.68235296011,1]},{"i":{"x":[0.833],"y":[0.833]},"o":{"x":[0.167],"y":[0.167]},"t":93.889,"s":[0.121568627656,0.843137264252,0.68235296011,1],"e":[0.121568627656,0.843137264252,0.68235296011,1]},{"i":{"x":[0.833],"y":[0.833]},"o":{"x":[0.167],"y":[0.167]},"t":102.573,"s":[0.121568627656,0.843137264252,0.68235296011,1],"e":[0.790025889874,0.807454049587,0.828094363213,1]},{"t":105.799590416882}],"ix":3},"o":{"a":0,"k":100,"ix":4},"w":{"a":0,"k":6,"ix":5},"lc":2,"lj":1,"ml":4,"bm":0,"nm":"描边 1","mn":"ADBE Vector Graphic - Stroke","hd":false},{"ty":"tm","s":{"a":1,"k":[{"i":{"x":[0.833],"y":[0.833]},"o":{"x":[0.167],"y":[0.167]},"t":91.327,"s":[60],"e":[42]},{"i":{"x":[0.833],"y":[0.833]},"o":{"x":[0.167],"y":[0.167]},"t":98.563,"s":[42],"e":[60]},{"t":105.799590416882}],"ix":1},"e":{"a":0,"k":67,"ix":2},"o":{"a":0,"k":0,"ix":3},"m":1,"ix":3,"nm":"Trim Paths","mn":"ADBE Vector Filter - Trim","hd":false},{"ty":"tr","p":{"a":0,"k":[0,234],"ix":2},"a":{"a":0,"k":[0,234],"ix":1},"s":{"a":0,"k":[100,100],"ix":3},"r":{"a":0,"k":282,"ix":6},"o":{"a":0,"k":100,"ix":7},"sk":{"a":0,"k":0,"ix":4},"sa":{"a":0,"k":0,"ix":5},"nm":"Transform"}],"nm":"形状 48","np":3,"cix":2,"bm":0,"ix":48,"mn":"ADBE Vector Group","hd":false},{"ty":"gr","it":[{"ind":0,"ty":"sh","ix":1,"ks":{"a":0,"k":{"i":[[0,0],[0,0]],"o":[[0,0],[0,0]],"v":[[0.75,-80],[0.75,24]],"c":false},"ix":2},"nm":"路径 1","mn":"ADBE Vector Shape - Group","hd":false},{"ty":"st","c":{"a":1,"k":[{"i":{"x":[0.833],"y":[0.833]},"o":{"x":[0.167],"y":[0.167]},"t":92.514,"s":[0.790025889874,0.807454049587,0.828094363213,1],"e":[0.121568627656,0.843137264252,0.68235296011,1]},{"i":{"x":[0.833],"y":[0.833]},"o":{"x":[0.167],"y":[0.167]},"t":95.336,"s":[0.121568627656,0.843137264252,0.68235296011,1],"e":[0.121568627656,0.843137264252,0.68235296011,1]},{"i":{"x":[0.833],"y":[0.833]},"o":{"x":[0.167],"y":[0.167]},"t":104.02,"s":[0.121568627656,0.843137264252,0.68235296011,1],"e":[0.790025889874,0.807454049587,0.828094363213,1]},{"t":106.986616502923}],"ix":3},"o":{"a":0,"k":100,"ix":4},"w":{"a":0,"k":6,"ix":5},"lc":2,"lj":1,"ml":4,"bm":0,"nm":"描边 1","mn":"ADBE Vector Graphic - Stroke","hd":false},{"ty":"tm","s":{"a":1,"k":[{"i":{"x":[0.833],"y":[0.833]},"o":{"x":[0.167],"y":[0.167]},"t":92.514,"s":[60],"e":[42]},{"i":{"x":[0.833],"y":[0.833]},"o":{"x":[0.167],"y":[0.167]},"t":99.75,"s":[42],"e":[60]},{"t":106.986616502923}],"ix":1},"e":{"a":0,"k":67,"ix":2},"o":{"a":0,"k":0,"ix":3},"m":1,"ix":3,"nm":"Trim Paths","mn":"ADBE Vector Filter - Trim","hd":false},{"ty":"tr","p":{"a":0,"k":[0,234],"ix":2},"a":{"a":0,"k":[0,234],"ix":1},"s":{"a":0,"k":[100,100],"ix":3},"r":{"a":0,"k":288,"ix":6},"o":{"a":0,"k":100,"ix":7},"sk":{"a":0,"k":0,"ix":4},"sa":{"a":0,"k":0,"ix":5},"nm":"Transform"}],"nm":"形状 49","np":3,"cix":2,"bm":0,"ix":49,"mn":"ADBE Vector Group","hd":false},{"ty":"gr","it":[{"ind":0,"ty":"sh","ix":1,"ks":{"a":0,"k":{"i":[[0,0],[0,0]],"o":[[0,0],[0,0]],"v":[[0.75,-80],[0.75,24]],"c":false},"ix":2},"nm":"路径 1","mn":"ADBE Vector Shape - Group","hd":false},{"ty":"st","c":{"a":1,"k":[{"i":{"x":[0.833],"y":[0.833]},"o":{"x":[0.167],"y":[0.167]},"t":93.686,"s":[0.790025889874,0.807454049587,0.828094363213,1],"e":[0.121568627656,0.843137264252,0.68235296011,1]},{"i":{"x":[0.833],"y":[0.833]},"o":{"x":[0.167],"y":[0.167]},"t":96.783,"s":[0.121568627656,0.843137264252,0.68235296011,1],"e":[0.121568627656,0.843137264252,0.68235296011,1]},{"i":{"x":[0.833],"y":[0.833]},"o":{"x":[0.167],"y":[0.167]},"t":105.467,"s":[0.121568627656,0.843137264252,0.68235296011,1],"e":[0.790025889874,0.807454049587,0.828094363213,1]},{"t":108.158645713615}],"ix":3},"o":{"a":0,"k":100,"ix":4},"w":{"a":0,"k":6,"ix":5},"lc":2,"lj":1,"ml":4,"bm":0,"nm":"描边 1","mn":"ADBE Vector Graphic - Stroke","hd":false},{"ty":"tm","s":{"a":1,"k":[{"i":{"x":[0.833],"y":[0.833]},"o":{"x":[0.167],"y":[0.167]},"t":93.686,"s":[60],"e":[42]},{"i":{"x":[0.833],"y":[0.833]},"o":{"x":[0.167],"y":[0.167]},"t":100.922,"s":[42],"e":[60]},{"t":108.158645713615}],"ix":1},"e":{"a":0,"k":67,"ix":2},"o":{"a":0,"k":0,"ix":3},"m":1,"ix":3,"nm":"Trim Paths","mn":"ADBE Vector Filter - Trim","hd":false},{"ty":"tr","p":{"a":0,"k":[0,234],"ix":2},"a":{"a":0,"k":[0,234],"ix":1},"s":{"a":0,"k":[100,100],"ix":3},"r":{"a":0,"k":294,"ix":6},"o":{"a":0,"k":100,"ix":7},"sk":{"a":0,"k":0,"ix":4},"sa":{"a":0,"k":0,"ix":5},"nm":"Transform"}],"nm":"形状 50","np":3,"cix":2,"bm":0,"ix":50,"mn":"ADBE Vector Group","hd":false},{"ty":"gr","it":[{"ind":0,"ty":"sh","ix":1,"ks":{"a":0,"k":{"i":[[0,0],[0,0]],"o":[[0,0],[0,0]],"v":[[0.75,-80],[0.75,24]],"c":false},"ix":2},"nm":"路径 1","mn":"ADBE Vector Shape - Group","hd":false},{"ty":"st","c":{"a":1,"k":[{"i":{"x":[0.833],"y":[0.833]},"o":{"x":[0.167],"y":[0.167]},"t":94.859,"s":[0.790025889874,0.807454049587,0.828094363213,1],"e":[0.121568627656,0.843137264252,0.68235296011,1]},{"i":{"x":[0.833],"y":[0.833]},"o":{"x":[0.167],"y":[0.167]},"t":97.753,"s":[0.121568627656,0.843137264252,0.68235296011,1],"e":[0.121568627656,0.843137264252,0.68235296011,1]},{"i":{"x":[0.833],"y":[0.833]},"o":{"x":[0.167],"y":[0.167]},"t":106.437,"s":[0.121568627656,0.843137264252,0.68235296011,1],"e":[0.790025889874,0.807454049587,0.828094363213,1]},{"t":109.33067103186}],"ix":3},"o":{"a":0,"k":100,"ix":4},"w":{"a":0,"k":6,"ix":5},"lc":2,"lj":1,"ml":4,"bm":0,"nm":"描边 1","mn":"ADBE Vector Graphic - Stroke","hd":false},{"ty":"tm","s":{"a":1,"k":[{"i":{"x":[0.833],"y":[0.833]},"o":{"x":[0.167],"y":[0.167]},"t":94.859,"s":[60],"e":[42]},{"i":{"x":[0.833],"y":[0.833]},"o":{"x":[0.167],"y":[0.167]},"t":102.095,"s":[42],"e":[60]},{"t":109.33067103186}],"ix":1},"e":{"a":0,"k":67,"ix":2},"o":{"a":0,"k":0,"ix":3},"m":1,"ix":3,"nm":"Trim Paths","mn":"ADBE Vector Filter - Trim","hd":false},{"ty":"tr","p":{"a":0,"k":[0,234],"ix":2},"a":{"a":0,"k":[0,234],"ix":1},"s":{"a":0,"k":[100,100],"ix":3},"r":{"a":0,"k":300,"ix":6},"o":{"a":0,"k":100,"ix":7},"sk":{"a":0,"k":0,"ix":4},"sa":{"a":0,"k":0,"ix":5},"nm":"Transform"}],"nm":"形状 51","np":3,"cix":2,"bm":0,"ix":51,"mn":"ADBE Vector Group","hd":false},{"ty":"gr","it":[{"ind":0,"ty":"sh","ix":1,"ks":{"a":0,"k":{"i":[[0,0],[0,0]],"o":[[0,0],[0,0]],"v":[[0.75,-80],[0.75,24]],"c":false},"ix":2},"nm":"路径 1","mn":"ADBE Vector Shape - Group","hd":false},{"ty":"st","c":{"a":1,"k":[{"i":{"x":[0.833],"y":[0.833]},"o":{"x":[0.167],"y":[0.167]},"t":96.045,"s":[0.790025889874,0.807454049587,0.828094363213,1],"e":[0.121568627656,0.843137264252,0.68235296011,1]},{"i":{"x":[0.833],"y":[0.833]},"o":{"x":[0.167],"y":[0.167]},"t":98.94,"s":[0.121568627656,0.843137264252,0.68235296011,1],"e":[0.121568627656,0.843137264252,0.68235296011,1]},{"i":{"x":[0.833],"y":[0.833]},"o":{"x":[0.167],"y":[0.167]},"t":106.915,"s":[0.121568627656,0.843137264252,0.68235296011,1],"e":[0.790025889874,0.807454049587,0.828094363213,1]},{"t":110.517692334841}],"ix":3},"o":{"a":0,"k":100,"ix":4},"w":{"a":0,"k":6,"ix":5},"lc":2,"lj":1,"ml":4,"bm":0,"nm":"描边 1","mn":"ADBE Vector Graphic - Stroke","hd":false},{"ty":"tm","s":{"a":1,"k":[{"i":{"x":[0.833],"y":[0.833]},"o":{"x":[0.167],"y":[0.167]},"t":96.045,"s":[60],"e":[42]},{"i":{"x":[0.833],"y":[0.833]},"o":{"x":[0.167],"y":[0.167]},"t":103.282,"s":[42],"e":[60]},{"t":110.517692334841}],"ix":1},"e":{"a":0,"k":67,"ix":2},"o":{"a":0,"k":0,"ix":3},"m":1,"ix":3,"nm":"Trim Paths","mn":"ADBE Vector Filter - Trim","hd":false},{"ty":"tr","p":{"a":0,"k":[0,234],"ix":2},"a":{"a":0,"k":[0,234],"ix":1},"s":{"a":0,"k":[100,100],"ix":3},"r":{"a":0,"k":306,"ix":6},"o":{"a":0,"k":100,"ix":7},"sk":{"a":0,"k":0,"ix":4},"sa":{"a":0,"k":0,"ix":5},"nm":"Transform"}],"nm":"形状 52","np":3,"cix":2,"bm":0,"ix":52,"mn":"ADBE Vector Group","hd":false},{"ty":"gr","it":[{"ind":0,"ty":"sh","ix":1,"ks":{"a":0,"k":{"i":[[0,0],[0,0]],"o":[[0,0],[0,0]],"v":[[0.75,-80],[0.75,24]],"c":false},"ix":2},"nm":"路径 1","mn":"ADBE Vector Shape - Group","hd":false},{"ty":"st","c":{"a":1,"k":[{"i":{"x":[0.833],"y":[0.833]},"o":{"x":[0.167],"y":[0.167]},"t":97.217,"s":[0.790025889874,0.807454049587,0.828094363213,1],"e":[0.121568627656,0.843137264252,0.68235296011,1]},{"i":{"x":[0.833],"y":[0.833]},"o":{"x":[0.167],"y":[0.167]},"t":99.678,"s":[0.121568627656,0.843137264252,0.68235296011,1],"e":[0.121568627656,0.843137264252,0.68235296011,1]},{"i":{"x":[0.833],"y":[0.833]},"o":{"x":[0.167],"y":[0.167]},"t":108.362,"s":[0.121568627656,0.843137264252,0.68235296011,1],"e":[0.790025889874,0.807454049587,0.828094363213,1]},{"t":111.689721545532}],"ix":3},"o":{"a":0,"k":100,"ix":4},"w":{"a":0,"k":6,"ix":5},"lc":2,"lj":1,"ml":4,"bm":0,"nm":"描边 1","mn":"ADBE Vector Graphic - Stroke","hd":false},{"ty":"tm","s":{"a":1,"k":[{"i":{"x":[0.833],"y":[0.833]},"o":{"x":[0.167],"y":[0.167]},"t":97.217,"s":[60],"e":[42]},{"i":{"x":[0.833],"y":[0.833]},"o":{"x":[0.167],"y":[0.167]},"t":104.454,"s":[42],"e":[60]},{"t":111.689721545532}],"ix":1},"e":{"a":0,"k":67,"ix":2},"o":{"a":0,"k":0,"ix":3},"m":1,"ix":3,"nm":"Trim Paths","mn":"ADBE Vector Filter - Trim","hd":false},{"ty":"tr","p":{"a":0,"k":[0,234],"ix":2},"a":{"a":0,"k":[0,234],"ix":1},"s":{"a":0,"k":[100,100],"ix":3},"r":{"a":0,"k":312,"ix":6},"o":{"a":0,"k":100,"ix":7},"sk":{"a":0,"k":0,"ix":4},"sa":{"a":0,"k":0,"ix":5},"nm":"Transform"}],"nm":"形状 53","np":3,"cix":2,"bm":0,"ix":53,"mn":"ADBE Vector Group","hd":false},{"ty":"gr","it":[{"ind":0,"ty":"sh","ix":1,"ks":{"a":0,"k":{"i":[[0,0],[0,0]],"o":[[0,0],[0,0]],"v":[[0.75,-80],[0.75,24]],"c":false},"ix":2},"nm":"路径 1","mn":"ADBE Vector Shape - Group","hd":false},{"ty":"st","c":{"a":1,"k":[{"i":{"x":[0.833],"y":[0.833]},"o":{"x":[0.167],"y":[0.167]},"t":98.39,"s":[0.790025889874,0.807454049587,0.828094363213,1],"e":[0.121568627656,0.843137264252,0.68235296011,1]},{"i":{"x":[0.833],"y":[0.833]},"o":{"x":[0.167],"y":[0.167]},"t":101.125,"s":[0.121568627656,0.843137264252,0.68235296011,1],"e":[0.121568627656,0.843137264252,0.68235296011,1]},{"i":{"x":[0.833],"y":[0.833]},"o":{"x":[0.167],"y":[0.167]},"t":109.809,"s":[0.121568627656,0.843137264252,0.68235296011,1],"e":[0.790025889874,0.807454049587,0.828094363213,1]},{"t":112.862745396487}],"ix":3},"o":{"a":0,"k":100,"ix":4},"w":{"a":0,"k":6,"ix":5},"lc":2,"lj":1,"ml":4,"bm":0,"nm":"描边 1","mn":"ADBE Vector Graphic - Stroke","hd":false},{"ty":"tm","s":{"a":1,"k":[{"i":{"x":[0.833],"y":[0.833]},"o":{"x":[0.167],"y":[0.167]},"t":98.39,"s":[60],"e":[42]},{"i":{"x":[0.833],"y":[0.833]},"o":{"x":[0.167],"y":[0.167]},"t":105.627,"s":[42],"e":[60]},{"t":112.862745396487}],"ix":1},"e":{"a":0,"k":67,"ix":2},"o":{"a":0,"k":0,"ix":3},"m":1,"ix":3,"nm":"Trim Paths","mn":"ADBE Vector Filter - Trim","hd":false},{"ty":"tr","p":{"a":0,"k":[0,234],"ix":2},"a":{"a":0,"k":[0,234],"ix":1},"s":{"a":0,"k":[100,100],"ix":3},"r":{"a":0,"k":318,"ix":6},"o":{"a":0,"k":100,"ix":7},"sk":{"a":0,"k":0,"ix":4},"sa":{"a":0,"k":0,"ix":5},"nm":"Transform"}],"nm":"形状 54","np":3,"cix":2,"bm":0,"ix":54,"mn":"ADBE Vector Group","hd":false},{"ty":"gr","it":[{"ind":0,"ty":"sh","ix":1,"ks":{"a":0,"k":{"i":[[0,0],[0,0]],"o":[[0,0],[0,0]],"v":[[0.75,-80],[0.75,24]],"c":false},"ix":2},"nm":"路径 1","mn":"ADBE Vector Shape - Group","hd":false},{"ty":"st","c":{"a":1,"k":[{"i":{"x":[0.833],"y":[0.833]},"o":{"x":[0.167],"y":[0.167]},"t":99.576,"s":[0.790025889874,0.807454049587,0.828094363213,1],"e":[0.121568627656,0.843137264252,0.68235296011,1]},{"i":{"x":[0.833],"y":[0.833]},"o":{"x":[0.167],"y":[0.167]},"t":102.472,"s":[0.121568627656,0.843137264252,0.68235296011,1],"e":[0.121568627656,0.843137264252,0.68235296011,1]},{"i":{"x":[0.833],"y":[0.833]},"o":{"x":[0.167],"y":[0.167]},"t":111.155,"s":[0.121568627656,0.843137264252,0.68235296011,1],"e":[0.790025889874,0.807454049587,0.828094363213,1]},{"t":114.048778191782}],"ix":3},"o":{"a":0,"k":100,"ix":4},"w":{"a":0,"k":6,"ix":5},"lc":2,"lj":1,"ml":4,"bm":0,"nm":"描边 1","mn":"ADBE Vector Graphic - Stroke","hd":false},{"ty":"tm","s":{"a":1,"k":[{"i":{"x":[0.833],"y":[0.833]},"o":{"x":[0.167],"y":[0.167]},"t":99.576,"s":[60],"e":[42]},{"i":{"x":[0.833],"y":[0.833]},"o":{"x":[0.167],"y":[0.167]},"t":106.813,"s":[42],"e":[60]},{"t":114.048778191782}],"ix":1},"e":{"a":0,"k":67,"ix":2},"o":{"a":0,"k":0,"ix":3},"m":1,"ix":3,"nm":"Trim Paths","mn":"ADBE Vector Filter - Trim","hd":false},{"ty":"tr","p":{"a":0,"k":[0,234],"ix":2},"a":{"a":0,"k":[0,234],"ix":1},"s":{"a":0,"k":[100,100],"ix":3},"r":{"a":0,"k":324,"ix":6},"o":{"a":0,"k":100,"ix":7},"sk":{"a":0,"k":0,"ix":4},"sa":{"a":0,"k":0,"ix":5},"nm":"Transform"}],"nm":"形状 55","np":3,"cix":2,"bm":0,"ix":55,"mn":"ADBE Vector Group","hd":false},{"ty":"gr","it":[{"ind":0,"ty":"sh","ix":1,"ks":{"a":0,"k":{"i":[[0,0],[0,0]],"o":[[0,0],[0,0]],"v":[[0.75,-80],[0.75,24]],"c":false},"ix":2},"nm":"路径 1","mn":"ADBE Vector Shape - Group","hd":false},{"ty":"st","c":{"a":1,"k":[{"i":{"x":[0.833],"y":[0.833]},"o":{"x":[0.167],"y":[0.167]},"t":100.749,"s":[0.790025889874,0.807454049587,0.828094363213,1],"e":[0.121568627656,0.843137264252,0.68235296011,1]},{"i":{"x":[0.833],"y":[0.833]},"o":{"x":[0.167],"y":[0.167]},"t":104.02,"s":[0.121568627656,0.843137264252,0.68235296011,1],"e":[0.121568627656,0.843137264252,0.68235296011,1]},{"i":{"x":[0.833],"y":[0.833]},"o":{"x":[0.167],"y":[0.167]},"t":112.703,"s":[0.121568627656,0.843137264252,0.68235296011,1],"e":[0.790025889874,0.807454049587,0.828094363213,1]},{"t":115.22180345036}],"ix":3},"o":{"a":0,"k":100,"ix":4},"w":{"a":0,"k":6,"ix":5},"lc":2,"lj":1,"ml":4,"bm":0,"nm":"描边 1","mn":"ADBE Vector Graphic - Stroke","hd":false},{"ty":"tm","s":{"a":1,"k":[{"i":{"x":[0.833],"y":[0.833]},"o":{"x":[0.167],"y":[0.167]},"t":100.749,"s":[60],"e":[42]},{"i":{"x":[0.833],"y":[0.833]},"o":{"x":[0.167],"y":[0.167]},"t":107.986,"s":[42],"e":[60]},{"t":115.22180345036}],"ix":1},"e":{"a":0,"k":67,"ix":2},"o":{"a":0,"k":0,"ix":3},"m":1,"ix":3,"nm":"Trim Paths","mn":"ADBE Vector Filter - Trim","hd":false},{"ty":"tr","p":{"a":0,"k":[0,234],"ix":2},"a":{"a":0,"k":[0,234],"ix":1},"s":{"a":0,"k":[100,100],"ix":3},"r":{"a":0,"k":330,"ix":6},"o":{"a":0,"k":100,"ix":7},"sk":{"a":0,"k":0,"ix":4},"sa":{"a":0,"k":0,"ix":5},"nm":"Transform"}],"nm":"形状 56","np":3,"cix":2,"bm":0,"ix":56,"mn":"ADBE Vector Group","hd":false},{"ty":"gr","it":[{"ind":0,"ty":"sh","ix":1,"ks":{"a":0,"k":{"i":[[0,0],[0,0]],"o":[[0,0],[0,0]],"v":[[0.75,-80],[0.75,24]],"c":false},"ix":2},"nm":"路径 1","mn":"ADBE Vector Shape - Group","hd":false},{"ty":"st","c":{"a":1,"k":[{"i":{"x":[0.833],"y":[0.833]},"o":{"x":[0.167],"y":[0.167]},"t":101.921,"s":[0.790025889874,0.807454049587,0.828094363213,1],"e":[0.121568627656,0.843137264252,0.68235296011,1]},{"i":{"x":[0.833],"y":[0.833]},"o":{"x":[0.167],"y":[0.167]},"t":104.816,"s":[0.121568627656,0.843137264252,0.68235296011,1],"e":[0.121568627656,0.843137264252,0.68235296011,1]},{"i":{"x":[0.833],"y":[0.833]},"o":{"x":[0.167],"y":[0.167]},"t":114.151,"s":[0.121568627656,0.843137264252,0.68235296011,1],"e":[0.790025889874,0.807454049587,0.828094363213,1]},{"t":116.393832661051}],"ix":3},"o":{"a":0,"k":100,"ix":4},"w":{"a":0,"k":6,"ix":5},"lc":2,"lj":1,"ml":4,"bm":0,"nm":"描边 1","mn":"ADBE Vector Graphic - Stroke","hd":false},{"ty":"tm","s":{"a":1,"k":[{"i":{"x":[0.833],"y":[0.833]},"o":{"x":[0.167],"y":[0.167]},"t":101.921,"s":[60],"e":[42]},{"i":{"x":[0.833],"y":[0.833]},"o":{"x":[0.167],"y":[0.167]},"t":109.158,"s":[42],"e":[60]},{"t":116.393832661051}],"ix":1},"e":{"a":0,"k":67,"ix":2},"o":{"a":0,"k":0,"ix":3},"m":1,"ix":3,"nm":"Trim Paths","mn":"ADBE Vector Filter - Trim","hd":false},{"ty":"tr","p":{"a":0,"k":[0,234],"ix":2},"a":{"a":0,"k":[0,234],"ix":1},"s":{"a":0,"k":[100,100],"ix":3},"r":{"a":0,"k":336,"ix":6},"o":{"a":0,"k":100,"ix":7},"sk":{"a":0,"k":0,"ix":4},"sa":{"a":0,"k":0,"ix":5},"nm":"Transform"}],"nm":"形状 57","np":3,"cix":2,"bm":0,"ix":57,"mn":"ADBE Vector Group","hd":false},{"ty":"gr","it":[{"ind":0,"ty":"sh","ix":1,"ks":{"a":0,"k":{"i":[[0,0],[0,0]],"o":[[0,0],[0,0]],"v":[[0.75,-80],[0.75,24]],"c":false},"ix":2},"nm":"路径 1","mn":"ADBE Vector Shape - Group","hd":false},{"ty":"st","c":{"a":1,"k":[{"i":{"x":[0.833],"y":[0.833]},"o":{"x":[0.167],"y":[0.167]},"t":103.109,"s":[0.790025889874,0.807454049587,0.828094363213,1],"e":[0.121568627656,0.843137264252,0.68235296011,1]},{"i":{"x":[0.833],"y":[0.833]},"o":{"x":[0.167],"y":[0.167]},"t":105.467,"s":[0.121568627656,0.843137264252,0.68235296011,1],"e":[0.121568627656,0.843137264252,0.68235296011,1]},{"i":{"x":[0.833],"y":[0.833]},"o":{"x":[0.167],"y":[0.167]},"t":114.151,"s":[0.121568627656,0.843137264252,0.68235296011,1],"e":[0.790025889874,0.807454049587,0.828094363213,1]},{"t":117.580859384614}],"ix":3},"o":{"a":0,"k":100,"ix":4},"w":{"a":0,"k":6,"ix":5},"lc":2,"lj":1,"ml":4,"bm":0,"nm":"描边 1","mn":"ADBE Vector Graphic - Stroke","hd":false},{"ty":"tm","s":{"a":1,"k":[{"i":{"x":[0.833],"y":[0.833]},"o":{"x":[0.167],"y":[0.167]},"t":103.109,"s":[60],"e":[42]},{"i":{"x":[0.833],"y":[0.833]},"o":{"x":[0.167],"y":[0.167]},"t":110.345,"s":[42],"e":[60]},{"t":117.580859384614}],"ix":1},"e":{"a":0,"k":67,"ix":2},"o":{"a":0,"k":0,"ix":3},"m":1,"ix":3,"nm":"Trim Paths","mn":"ADBE Vector Filter - Trim","hd":false},{"ty":"tr","p":{"a":0,"k":[0,234],"ix":2},"a":{"a":0,"k":[0,234],"ix":1},"s":{"a":0,"k":[100,100],"ix":3},"r":{"a":0,"k":342,"ix":6},"o":{"a":0,"k":100,"ix":7},"sk":{"a":0,"k":0,"ix":4},"sa":{"a":0,"k":0,"ix":5},"nm":"Transform"}],"nm":"形状 58","np":3,"cix":2,"bm":0,"ix":58,"mn":"ADBE Vector Group","hd":false},{"ty":"gr","it":[{"ind":0,"ty":"sh","ix":1,"ks":{"a":0,"k":{"i":[[0,0],[0,0]],"o":[[0,0],[0,0]],"v":[[0.75,-80],[0.75,24]],"c":false},"ix":2},"nm":"路径 1","mn":"ADBE Vector Shape - Group","hd":false},{"ty":"st","c":{"a":1,"k":[{"i":{"x":[0.833],"y":[0.833]},"o":{"x":[0.167],"y":[0.167]},"t":104.281,"s":[0.790025889874,0.807454049587,0.828094363213,1],"e":[0.121568627656,0.843137264252,0.68235296011,1]},{"i":{"x":[0.833],"y":[0.833]},"o":{"x":[0.167],"y":[0.167]},"t":106.915,"s":[0.121568627656,0.843137264252,0.68235296011,1],"e":[0.121568627656,0.843137264252,0.68235296011,1]},{"i":{"x":[0.833],"y":[0.833]},"o":{"x":[0.167],"y":[0.167]},"t":115.858,"s":[0.121568627656,0.843137264252,0.68235296011,1],"e":[0.790025889874,0.807454049587,0.828094363213,1]},{"t":118.752886142121}],"ix":3},"o":{"a":0,"k":100,"ix":4},"w":{"a":0,"k":6,"ix":5},"lc":2,"lj":1,"ml":4,"bm":0,"nm":"描边 1","mn":"ADBE Vector Graphic - Stroke","hd":false},{"ty":"tm","s":{"a":1,"k":[{"i":{"x":[0.833],"y":[0.833]},"o":{"x":[0.167],"y":[0.167]},"t":104.281,"s":[60],"e":[42]},{"i":{"x":[0.833],"y":[0.833]},"o":{"x":[0.167],"y":[0.167]},"t":111.517,"s":[42],"e":[60]},{"t":118.752886142121}],"ix":1},"e":{"a":0,"k":67,"ix":2},"o":{"a":0,"k":0,"ix":3},"m":1,"ix":3,"nm":"Trim Paths","mn":"ADBE Vector Filter - Trim","hd":false},{"ty":"tr","p":{"a":0,"k":[0,234],"ix":2},"a":{"a":0,"k":[0,234],"ix":1},"s":{"a":0,"k":[100,100],"ix":3},"r":{"a":0,"k":348,"ix":6},"o":{"a":0,"k":100,"ix":7},"sk":{"a":0,"k":0,"ix":4},"sa":{"a":0,"k":0,"ix":5},"nm":"Transform"}],"nm":"形状 59","np":3,"cix":2,"bm":0,"ix":59,"mn":"ADBE Vector Group","hd":false},{"ty":"gr","it":[{"ind":0,"ty":"sh","ix":1,"ks":{"a":0,"k":{"i":[[0,0],[0,0]],"o":[[0,0],[0,0]],"v":[[0.75,-80],[0.75,24]],"c":false},"ix":2},"nm":"路径 1","mn":"ADBE Vector Shape - Group","hd":false},{"ty":"st","c":{"a":1,"k":[{"i":{"x":[0.833],"y":[0.833]},"o":{"x":[0.167],"y":[0.167]},"t":105.453,"s":[0.790025889874,0.807454049587,0.828094363213,1],"e":[0.121568627656,0.843137264252,0.68235296011,1]},{"i":{"x":[0.833],"y":[0.833]},"o":{"x":[0.167],"y":[0.167]},"t":108.362,"s":[0.121568627656,0.843137264252,0.68235296011,1],"e":[0.121568627656,0.843137264252,0.68235296011,1]},{"i":{"x":[0.833],"y":[0.833]},"o":{"x":[0.167],"y":[0.167]},"t":117.045,"s":[0.121568627656,0.843137264252,0.68235296011,1],"e":[0.790025889874,0.807454049587,0.828094363213,1]},{"t":119.924908492969}],"ix":3},"o":{"a":0,"k":100,"ix":4},"w":{"a":0,"k":6,"ix":5},"lc":2,"lj":1,"ml":4,"bm":0,"nm":"描边 1","mn":"ADBE Vector Graphic - Stroke","hd":false},{"ty":"tm","s":{"a":1,"k":[{"i":{"x":[0.833],"y":[0.833]},"o":{"x":[0.167],"y":[0.167]},"t":105.453,"s":[60],"e":[42]},{"i":{"x":[0.833],"y":[0.833]},"o":{"x":[0.167],"y":[0.167]},"t":112.689,"s":[42],"e":[60]},{"t":119.924908492969}],"ix":1},"e":{"a":0,"k":67,"ix":2},"o":{"a":0,"k":0,"ix":3},"m":1,"ix":3,"nm":"Trim Paths","mn":"ADBE Vector Filter - Trim","hd":false},{"ty":"tr","p":{"a":0,"k":[0,234],"ix":2},"a":{"a":0,"k":[0,234],"ix":1},"s":{"a":0,"k":[100,100],"ix":3},"r":{"a":0,"k":354,"ix":6},"o":{"a":0,"k":100,"ix":7},"sk":{"a":0,"k":0,"ix":4},"sa":{"a":0,"k":0,"ix":5},"nm":"Transform"}],"nm":"形状 60","np":3,"cix":2,"bm":0,"ix":60,"mn":"ADBE Vector Group","hd":false}],"ip":0,"op":119.999989613637,"st":35.9999968840911,"bm":0}],"markers":[]}